Workbook
Name Slicer_Delivery_Status: #N/A
Name Slicer_Payment_Method: #N/A
Name Slicer_Region: #N/A

Sheet Orders
A1: Order ID | B1: Customer ID | C1: Product ID | D1: Region | E1: Sale Price/Unit | F1: Quantity | G1: Total Amount | H1: Payment Method | I1: Delivery Status | J1: Fulfillment Partner | K1: Order Date | L1: Delivery Date | M1: Cancel Date | N1: Cancellation Status | O1: Product Category | P1: Delivery Time (Days) | Q1: Customer Name | R1: Delivery Performance | S1: Product Name
A2: ORD0001 | B2: CUST021 | C2: PROD012 | D2: North | E2: 44 | F2: 1 | G2: 44 | H2: Apple Pay | I2: Cancelled | J2: DHL | K2: 45291 | M2: 45293 | N2: =IF(OR(I2="Cancelled",M2<>""),"Yes","No") -> Yes | O2: =_xlfn.XLOOKUP(C2, 'Product Master'!$A$2:$A$23, 'Product Master'!$C$2:$C$23) -> Home | P2: =IF(L2<>"", L2-K2, "NA") -> NA | Q2: =IFERROR(_xlfn.XLOOKUP(B2,'Customer Master'!$A$1:$A$50,'Customer Master'!$B$1:$B$50),"Not Found") -> Zoe Mitchell | R2: {=_xlfn.IFS(P2="NA", "NA", P2<=2, "Fast", P2>2, "Slow")} -> NA | S2: =_xlfn.XLOOKUP(C2, 'Product Master'!$A$1:$A$23, 'Product Master'!$B$1:$B$23, "Not Found") -> Lamp
A3: ORD0002 | B3: CUST029 | C3: PROD018 | D3: East | E3: 96 | F3: 4 | G3: 384 | H3: Credit Card | I3: Delivered | J3: DHL | K3: 44979 | L3: 44981 | N3: =IF(OR(I3="Cancelled",M3<>""),"Yes","No") -> No | O3: =_xlfn.XLOOKUP(C3, 'Product Master'!$A$2:$A$23, 'Product Master'!$C$2:$C$23) -> Toys | P3: =IF(L3<>"", L3-K3, "NA") -> 2 | Q3: =IFERROR(_xlfn.XLOOKUP(B3,'Customer Master'!$A$1:$A$50,'Customer Master'!$B$1:$B$50),"Not Found") -> Ava White | R3: {=_xlfn.IFS(P3="NA", "NA", P3<=2, "Fast", P3>2, "Slow")} -> Fast | S3: =_xlfn.XLOOKUP(C3, 'Product Master'!$A$1:$A$23, 'Product Master'!$B$1:$B$23, "Not Found") -> Doll House
A4: ORD0003 | B4: CUST021 | C4: PROD013 | D4: South | E4: 194 | F4: 4 | G4: 776 | H4: Credit Card | I4: In Transit | J4: USPS | K4: 45210 | N4: =IF(OR(I4="Cancelled",M4<>""),"Yes","No") -> No | O4: =_xlfn.XLOOKUP(C4, 'Product Master'!$A$2:$A$23, 'Product Master'!$C$2:$C$23) -> Home | P4: =IF(L4<>"", L4-K4, "NA") -> NA | Q4: =IFERROR(_xlfn.XLOOKUP(B4,'Customer Master'!$A$1:$A$50,'Customer Master'!$B$1:$B$50),"Not Found") -> Zoe Mitchell | R4: {=_xlfn.IFS(P4="NA", "NA", P4<=2, "Fast", P4>2, "Slow")} -> NA | S4: =_xlfn.XLOOKUP(C4, 'Product Master'!$A$1:$A$23, 'Product Master'!$B$1:$B$23, "Not Found") -> Vacuum Cleaner
A5: ORD0004 | B5: CUST044 | C5: PROD013 | D5: North | E5: 196 | F5: 3 | G5: 588 | H5: PayPal | I5: Cancelled | J5: UPS | K5: 45051 | M5: 45057 | N5: =IF(OR(I5="Cancelled",M5<>""),"Yes","No") -> Yes | O5: =_xlfn.XLOOKUP(C5, 'Product Master'!$A$2:$A$23, 'Product Master'!$C$2:$C$23) -> Home | P5: =IF(L5<>"", L5-K5, "NA") -> NA | Q5: =IFERROR(_xlfn.XLOOKUP(B5,'Customer Master'!$A$1:$A$50,'Customer Master'!$B$1:$B$50),"Not Found") -> Grace Ward | R5: {=_xlfn.IFS(P5="NA", "NA", P5<=2, "Fast", P5>2, "Slow")} -> NA | S5: =_xlfn.XLOOKUP(C5, 'Product Master'!$A$1:$A$23, 'Product Master'!$B$1:$B$23, "Not Found") -> Vacuum Cleaner
A6: ORD0005 | B6: CUST027 | C6: PROD010 | D6: North | E6: 59 | F6: 1 | G6: 59 | H6: PayPal | I6: Delivered | J6: Amazon Logistics | K6: 44959 | L6: 44962 | N6: =IF(OR(I6="Cancelled",M6<>""),"Yes","No") -> No | O6: =_xlfn.XLOOKUP(C6, 'Product Master'!$A$2:$A$23, 'Product Master'!$C$2:$C$23) -> Fashion | P6: =IF(L6<>"", L6-K6, "NA") -> 3 | Q6: =IFERROR(_xlfn.XLOOKUP(B6,'Customer Master'!$A$1:$A$50,'Customer Master'!$B$1:$B$50),"Not Found") -> Hazel Brooks | R6: {=_xlfn.IFS(P6="NA", "NA", P6<=2, "Fast", P6>2, "Slow")} -> Slow | S6: =_xlfn.XLOOKUP(C6, 'Product Master'!$A$1:$A$23, 'Product Master'!$B$1:$B$23, "Not Found") -> Jeans
A7: ORD0006 | B7: CUST009 | C7: PROD010 | D7: North | E7: 58 | F7: 4 | G7: 232 | H7: Amazon Pay | I7: Cancelled | J7: DHL | K7: 45231 | M7: 45232 | N7: =IF(OR(I7="Cancelled",M7<>""),"Yes","No") -> Yes | O7: =_xlfn.XLOOKUP(C7, 'Product Master'!$A$2:$A$23, 'Product Master'!$C$2:$C$23) -> Fashion | P7: =IF(L7<>"", L7-K7, "NA") -> NA | Q7: =IFERROR(_xlfn.XLOOKUP(B7,'Customer Master'!$A$1:$A$50,'Customer Master'!$B$1:$B$50),"Not Found") -> Jackson Allen | R7: {=_xlfn.IFS(P7="NA", "NA", P7<=2, "Fast", P7>2, "Slow")} -> NA | S7: =_xlfn.XLOOKUP(C7, 'Product Master'!$A$1:$A$23, 'Product Master'!$B$1:$B$23, "Not Found") -> Jeans
A8: ORD0007 | B8: CUST042 | C8: PROD020 | D8: Central | E8: 105 | F8: 3 | G8: 315 | H8: Debit Card | I8: Cancelled | J8: DHL | K8: 45152 | M8: 45156 | N8: =IF(OR(I8="Cancelled",M8<>""),"Yes","No") -> Yes | O8: =_xlfn.XLOOKUP(C8, 'Product Master'!$A$2:$A$23, 'Product Master'!$C$2:$C$23) -> Electronics | P8: =IF(L8<>"", L8-K8, "NA") -> NA | Q8: =IFERROR(_xlfn.XLOOKUP(B8,'Customer Master'!$A$1:$A$50,'Customer Master'!$B$1:$B$50),"Not Found") -> Noah Wilson | R8: {=_xlfn.IFS(P8="NA", "NA", P8<=2, "Fast", P8>2, "Slow")} -> NA | S8: =_xlfn.XLOOKUP(C8, 'Product Master'!$A$1:$A$23, 'Product Master'!$B$1:$B$23, "Not Found") -> Bluetooth Speaker
A9: ORD0008 | B9: CUST019 | C9: PROD021 | D9: West | E9: 37 | F9: 5 | G9: 185 | H9: PayPal | I9: Cancelled | J9: DHL | K9: 45017 | M9: 45022 | N9: =IF(OR(I9="Cancelled",M9<>""),"Yes","No") -> Yes | O9: =_xlfn.XLOOKUP(C9, 'Product Master'!$A$2:$A$23, 'Product Master'!$C$2:$C$23) -> Home | P9: =IF(L9<>"", L9-K9, "NA") -> NA | Q9: =IFERROR(_xlfn.XLOOKUP(B9,'Customer Master'!$A$1:$A$50,'Customer Master'!$B$1:$B$50),"Not Found") -> Ava Robinson | R9: {=_xlfn.IFS(P9="NA", "NA", P9<=2, "Fast", P9>2, "Slow")} -> NA | S9: =_xlfn.XLOOKUP(C9, 'Product Master'!$A$1:$A$23, 'Product Master'!$B$1:$B$23, "Not Found") -> Wall Clock
A10: ORD0009 | B10: CUST013 | C10: PROD019 | D10: Central | E10: 44 | F10: 2 | G10: 88 | H10: Credit Card | I10: In Transit | J10: Amazon Logistics | K10: 45128 | N10: =IF(OR(I10="Cancelled",M10<>""),"Yes","No") -> No | O10: =_xlfn.XLOOKUP(C10, 'Product Master'!$A$2:$A$23, 'Product Master'!$C$2:$C$23) -> Fashion | P10: =IF(L10<>"", L10-K10, "NA") -> NA | Q10: =IFERROR(_xlfn.XLOOKUP(B10,'Customer Master'!$A$1:$A$50,'Customer Master'!$B$1:$B$50),"Not Found") -> Olivia Martinez | R10: {=_xlfn.IFS(P10="NA", "NA", P10<=2, "Fast", P10>2, "Slow")} -> NA | S10: =_xlfn.XLOOKUP(C10, 'Product Master'!$A$1:$A$23, 'Product Master'!$B$1:$B$23, "Not Found") -> Formal Shirt
A11: ORD0010 | B11: CUST019 | C11: PROD003 | D11: South | E11: 141 | F11: 4 | G11: 564 | H11: Debit Card | I11: In Transit | J11: DHL | K11: 45289 | N11: =IF(OR(I11="Cancelled",M11<>""),"Yes","No") -> No | O11: =_xlfn.XLOOKUP(C11, 'Product Master'!$A$2:$A$23, 'Product Master'!$C$2:$C$23) -> Home | P11: =IF(L11<>"", L11-K11, "NA") -> NA | Q11: =IFERROR(_xlfn.XLOOKUP(B11,'Customer Master'!$A$1:$A$50,'Customer Master'!$B$1:$B$50),"Not Found") -> Ava Robinson | R11: {=_xlfn.IFS(P11="NA", "NA", P11<=2, "Fast", P11>2, "Slow")} -> NA | S11: =_xlfn.XLOOKUP(C11, 'Product Master'!$A$1:$A$23, 'Product Master'!$B$1:$B$23, "Not Found") -> Cookware Set
A12: ORD0011 | B12: CUST046 | C12: PROD014 | D12: South | E12: 249 | F12: 1 | G12: 249 | H12: Amazon Pay | I12: Cancelled | J12: USPS | K12: 45050 | M12: 45054 | N12: =IF(OR(I12="Cancelled",M12<>""),"Yes","No") -> Yes | O12: =_xlfn.XLOOKUP(C12, 'Product Master'!$A$2:$A$23, 'Product Master'!$C$2:$C$23) -> Electronics | P12: =IF(L12<>"", L12-K12, "NA") -> NA | Q12: =IFERROR(_xlfn.XLOOKUP(B12,'Customer Master'!$A$1:$A$50,'Customer Master'!$B$1:$B$50),"Not Found") -> Emily Johnson | R12: {=_xlfn.IFS(P12="NA", "NA", P12<=2, "Fast", P12>2, "Slow")} -> NA | S12: =_xlfn.XLOOKUP(C12, 'Product Master'!$A$1:$A$23, 'Product Master'!$B$1:$B$23, "Not Found") -> Smartwatch
A13: ORD0012 | B13: CUST045 | C13: PROD014 | D13: Central | E13: 247 | F13: 3 | G13: 741 | H13: Amazon Pay | I13: In Transit | J13: FedEx | K13: 45132 | N13: =IF(OR(I13="Cancelled",M13<>""),"Yes","No") -> No | O13: =_xlfn.XLOOKUP(C13, 'Product Master'!$A$2:$A$23, 'Product Master'!$C$2:$C$23) -> Electronics | P13: =IF(L13<>"", L13-K13, "NA") -> NA | Q13: =IFERROR(_xlfn.XLOOKUP(B13,'Customer Master'!$A$1:$A$50,'Customer Master'!$B$1:$B$50),"Not Found") -> Emily Johnson | R13: {=_xlfn.IFS(P13="NA", "NA", P13<=2, "Fast", P13>2, "Slow")} -> NA | S13: =_xlfn.XLOOKUP(C13, 'Product Master'!$A$1:$A$23, 'Product Master'!$B$1:$B$23, "Not Found") -> Smartwatch
A14: ORD0013 | B14: CUST023 | C14: PROD006 | D14: Central | E14: 96 | F14: 1 | G14: 96 | H14: Apple Pay | I14: Cancelled | J14: Amazon Logistics | K14: 44982 | M14: 44985 | N14: =IF(OR(I14="Cancelled",M14<>""),"Yes","No") -> Yes | O14: =_xlfn.XLOOKUP(C14, 'Product Master'!$A$2:$A$23, 'Product Master'!$C$2:$C$23) -> Fashion | P14: =IF(L14<>"", L14-K14, "NA") -> NA | Q14: =IFERROR(_xlfn.XLOOKUP(B14,'Customer Master'!$A$1:$A$50,'Customer Master'!$B$1:$B$50),"Not Found") -> Charlotte Reed | R14: {=_xlfn.IFS(P14="NA", "NA", P14<=2, "Fast", P14>2, "Slow")} -> NA | S14: =_xlfn.XLOOKUP(C14, 'Product Master'!$A$1:$A$23, 'Product Master'!$B$1:$B$23, "Not Found") -> Shoes
A15: ORD0014 | B15: CUST033 | C15: PROD017 | D15: West | E15: 74 | F15: 5 | G15: 370 | H15: Apple Pay | I15: Cancelled | J15: Amazon Logistics | K15: 44981 | M15: 44982 | N15: =IF(OR(I15="Cancelled",M15<>""),"Yes","No") -> Yes | O15: =_xlfn.XLOOKUP(C15, 'Product Master'!$A$2:$A$23, 'Product Master'!$C$2:$C$23) -> Electronics | P15: =IF(L15<>"", L15-K15, "NA") -> NA | Q15: =IFERROR(_xlfn.XLOOKUP(B15,'Customer Master'!$A$1:$A$50,'Customer Master'!$B$1:$B$50),"Not Found") -> Hazel Rivera | R15: {=_xlfn.IFS(P15="NA", "NA", P15<=2, "Fast", P15>2, "Slow")} -> NA | S15: =_xlfn.XLOOKUP(C15, 'Product Master'!$A$1:$A$23, 'Product Master'!$B$1:$B$23, "Not Found") -> Gaming Mouse
A16: ORD0015 | B16: CUST033 | C16: PROD005 | D16: South | E16: 27 | F16: 1 | G16: 27 | H16: Credit Card | I16: Cancelled | J16: Amazon Logistics | K16: 45164 | M16: 45171 | N16: =IF(OR(I16="Cancelled",M16<>""),"Yes","No") -> Yes | O16: =_xlfn.XLOOKUP(C16, 'Product Master'!$A$2:$A$23, 'Product Master'!$C$2:$C$23) -> Fashion | P16: =IF(L16<>"", L16-K16, "NA") -> NA | Q16: =IFERROR(_xlfn.XLOOKUP(B16,'Customer Master'!$A$1:$A$50,'Customer Master'!$B$1:$B$50),"Not Found") -> Hazel Rivera | R16: {=_xlfn.IFS(P16="NA", "NA", P16<=2, "Fast", P16>2, "Slow")} -> NA | S16: =_xlfn.XLOOKUP(C16, 'Product Master'!$A$1:$A$23, 'Product Master'!$B$1:$B$23, "Not Found") -> T-Shirt
A17: ORD0016 | B17: CUST047 | C17: PROD005 | D17: South | E17: 27 | F17: 3 | G17: 81 | H17: Debit Card | I17: In Transit | J17: Amazon Logistics | K17: 44970 | N17: =IF(OR(I17="Cancelled",M17<>""),"Yes","No") -> No | O17: =_xlfn.XLOOKUP(C17, 'Product Master'!$A$2:$A$23, 'Product Master'!$C$2:$C$23) -> Fashion | P17: =IF(L17<>"", L17-K17, "NA") -> NA | Q17: =IFERROR(_xlfn.XLOOKUP(B17,'Customer Master'!$A$1:$A$50,'Customer Master'!$B$1:$B$50),"Not Found") -> Scarlett Murphy | R17: {=_xlfn.IFS(P17="NA", "NA", P17<=2, "Fast", P17>2, "Slow")} -> NA | S17: =_xlfn.XLOOKUP(C17, 'Product Master'!$A$1:$A$23, 'Product Master'!$B$1:$B$23, "Not Found") -> T-Shirt
A18: ORD0017 | B18: CUST045 | C18: PROD015 | D18: East | E18: 21 | F18: 3 | G18: 63 | H18: Credit Card | I18: Delivered | J18: DHL | K18: 45105 | L18: 45108 | N18: =IF(OR(I18="Cancelled",M18<>""),"Yes","No") -> No | O18: =_xlfn.XLOOKUP(C18, 'Product Master'!$A$2:$A$23, 'Product Master'!$C$2:$C$23) -> Books | P18: =IF(L18<>"", L18-K18, "NA") -> 3 | Q18: =IFERROR(_xlfn.XLOOKUP(B18,'Customer Master'!$A$1:$A$50,'Customer Master'!$B$1:$B$50),"Not Found") -> Emily Johnson | R18: {=_xlfn.IFS(P18="NA", "NA", P18<=2, "Fast", P18>2, "Slow")} -> Slow | S18: =_xlfn.XLOOKUP(C18, 'Product Master'!$A$1:$A$23, 'Product Master'!$B$1:$B$23, "Not Found") -> Novel
A19: ORD0018 | B19: CUST011 | C19: PROD008 | D19: West | E19: 70 | F19: 5 | G19: 350 | H19: PayPal | I19: In Transit | J19: Amazon Logistics | K19: 45258 | N19: =IF(OR(I19="Cancelled",M19<>""),"Yes","No") -> No | O19: =_xlfn.XLOOKUP(C19, 'Product Master'!$A$2:$A$23, 'Product Master'!$C$2:$C$23) -> Books | P19: =IF(L19<>"", L19-K19, "NA") -> NA | Q19: =IFERROR(_xlfn.XLOOKUP(B19,'Customer Master'!$A$1:$A$50,'Customer Master'!$B$1:$B$50),"Not Found") -> Mason Hall | R19: {=_xlfn.IFS(P19="NA", "NA", P19<=2, "Fast", P19>2, "Slow")} -> NA | S19: =_xlfn.XLOOKUP(C19, 'Product Master'!$A$1:$A$23, 'Product Master'!$B$1:$B$23, "Not Found") -> Textbook
A20: ORD0019 | B20: CUST041 | C20: PROD006 | D20: South | E20: 94 | F20: 4 | G20: 376 | H20: Credit Card | I20: In Transit | J20: USPS | K20: 45163 | N20: =IF(OR(I20="Cancelled",M20<>""),"Yes","No") -> No | O20: =_xlfn.XLOOKUP(C20, 'Product Master'!$A$2:$A$23, 'Product Master'!$C$2:$C$23) -> Fashion | P20: =IF(L20<>"", L20-K20, "NA") -> NA | Q20: =IFERROR(_xlfn.XLOOKUP(B20,'Customer Master'!$A$1:$A$50,'Customer Master'!$B$1:$B$50),"Not Found") -> Jacob Price | R20: {=_xlfn.IFS(P20="NA", "NA", P20<=2, "Fast", P20>2, "Slow")} -> NA | S20: =_xlfn.XLOOKUP(C20, 'Product Master'!$A$1:$A$23, 'Product Master'!$B$1:$B$23, "Not Found") -> Shoes
A21: ORD0020 | B21: CUST025 | C21: PROD001 | D21: North | E21: 813 | F21: 2 | G21: 1626 | H21: Credit Card | I21: In Transit | J21: FedEx | K21: 45028 | N21: =IF(OR(I21="Cancelled",M21<>""),"Yes","No") -> No | O21: =_xlfn.XLOOKUP(C21, 'Product Master'!$A$2:$A$23, 'Product Master'!$C$2:$C$23) -> Electronics | P21: =IF(L21<>"", L21-K21, "NA") -> NA | Q21: =IFERROR(_xlfn.XLOOKUP(B21,'Customer Master'!$A$1:$A$50,'Customer Master'!$B$1:$B$50),"Not Found") -> Emma King | R21: {=_xlfn.IFS(P21="NA", "NA", P21<=2, "Fast", P21>2, "Slow")} -> NA | S21: =_xlfn.XLOOKUP(C21, 'Product Master'!$A$1:$A$23, 'Product Master'!$B$1:$B$23, "Not Found") -> Smartphone
A22: ORD0021 | B22: CUST013 | C22: PROD015 | D22: Central | E22: 21 | F22: 4 | G22: 84 | H22: PayPal | I22: In Transit | J22: Amazon Logistics | K22: 45201 | N22: =IF(OR(I22="Cancelled",M22<>""),"Yes","No") -> No | O22: =_xlfn.XLOOKUP(C22, 'Product Master'!$A$2:$A$23, 'Product Master'!$C$2:$C$23) -> Books | P22: =IF(L22<>"", L22-K22, "NA") -> NA | Q22: =IFERROR(_xlfn.XLOOKUP(B22,'Customer Master'!$A$1:$A$50,'Customer Master'!$B$1:$B$50),"Not Found") -> Olivia Martinez | R22: {=_xlfn.IFS(P22="NA", "NA", P22<=2, "Fast", P22>2, "Slow")} -> NA | S22: =_xlfn.XLOOKUP(C22, 'Product Master'!$A$1:$A$23, 'Product Master'!$B$1:$B$23, "Not Found") -> Novel
A23: ORD0022 | B23: CUST023 | C23: PROD012 | D23: West | E23: 46 | F23: 5 | G23: 230 | H23: PayPal | I23: In Transit | J23: USPS | K23: 45239 | N23: =IF(OR(I23="Cancelled",M23<>""),"Yes","No") -> No | O23: =_xlfn.XLOOKUP(C23, 'Product Master'!$A$2:$A$23, 'Product Master'!$C$2:$C$23) -> Home | P23: =IF(L23<>"", L23-K23, "NA") -> NA | Q23: =IFERROR(_xlfn.XLOOKUP(B23,'Customer Master'!$A$1:$A$50,'Customer Master'!$B$1:$B$50),"Not Found") -> Charlotte Reed | R23: {=_xlfn.IFS(P23="NA", "NA", P23<=2, "Fast", P23>2, "Slow")} -> NA | S23: =_xlfn.XLOOKUP(C23, 'Product Master'!$A$1:$A$23, 'Product Master'!$B$1:$B$23, "Not Found") -> Lamp
A24: ORD0023 | B24: CUST016 | C24: PROD010 | D24: West | E24: 58 | F24: 3 | G24: 174 | H24: Amazon Pay | I24: Cancelled | J24: Amazon Logistics | K24: 44970 | M24: 44971 | N24: =IF(OR(I24="Cancelled",M24<>""),"Yes","No") -> Yes | O24: =_xlfn.XLOOKUP(C24, 'Product Master'!$A$2:$A$23, 'Product Master'!$C$2:$C$23) -> Fashion | P24: =IF(L24<>"", L24-K24, "NA") -> NA | Q24: =IFERROR(_xlfn.XLOOKUP(B24,'Customer Master'!$A$1:$A$50,'Customer Master'!$B$1:$B$50),"Not Found") -> Elijah Lewis | R24: {=_xlfn.IFS(P24="NA", "NA", P24<=2, "Fast", P24>2, "Slow")} -> NA | S24: =_xlfn.XLOOKUP(C24, 'Product Master'!$A$1:$A$23, 'Product Master'!$B$1:$B$23, "Not Found") -> Jeans
A25: ORD0024 | B25: CUST028 | C25: PROD006 | D25: West | E25: 96 | F25: 5 | G25: 480 | H25: Amazon Pay | I25: Delivered | J25: Amazon Logistics | K25: 45232 | L25: 45235 | N25: =IF(OR(I25="Cancelled",M25<>""),"Yes","No") -> No | O25: =_xlfn.XLOOKUP(C25, 'Product Master'!$A$2:$A$23, 'Product Master'!$C$2:$C$23) -> Fashion | P25: =IF(L25<>"", L25-K25, "NA") -> 3 | Q25: =IFERROR(_xlfn.XLOOKUP(B25,'Customer Master'!$A$1:$A$50,'Customer Master'!$B$1:$B$50),"Not Found") -> Lily Bennett | R25: {=_xlfn.IFS(P25="NA", "NA", P25<=2, "Fast", P25>2, "Slow")} -> Slow | S25: =_xlfn.XLOOKUP(C25, 'Product Master'!$A$1:$A$23, 'Product Master'!$B$1:$B$23, "Not Found") -> Shoes
A26: ORD0025 | B26: CUST040 | C26: PROD002 | D26: South | E26: 43 | F26: 1 | G26: 43 | H26: Debit Card | I26: Delivered | J26: Amazon Logistics | K26: 45074 | L26: 45076 | N26: =IF(OR(I26="Cancelled",M26<>""),"Yes","No") -> No | O26: =_xlfn.XLOOKUP(C26, 'Product Master'!$A$2:$A$23, 'Product Master'!$C$2:$C$23) -> Toys | P26: =IF(L26<>"", L26-K26, "NA") -> 2 | Q26: =IFERROR(_xlfn.XLOOKUP(B26,'Customer Master'!$A$1:$A$50,'Customer Master'!$B$1:$B$50),"Not Found") -> Benjamin Clark | R26: {=_xlfn.IFS(P26="NA", "NA", P26<=2, "Fast", P26>2, "Slow")} -> Fast | S26: =_xlfn.XLOOKUP(C26, 'Product Master'!$A$1:$A$23, 'Product Master'!$B$1:$B$23, "Not Found") -> Action Figure
A27: ORD0026 | B27: CUST027 | C27: PROD022 | D27: South | E27: 64 | F27: 4 | G27: 256 | H27: Debit Card | I27: Delivered | J27: USPS | K27: 45214 | L27: 45220 | N27: =IF(OR(I27="Cancelled",M27<>""),"Yes","No") -> No | O27: =_xlfn.XLOOKUP(C27, 'Product Master'!$A$2:$A$23, 'Product Master'!$C$2:$C$23) -> Fashion | P27: =IF(L27<>"", L27-K27, "NA") -> 6 | Q27: =IFERROR(_xlfn.XLOOKUP(B27,'Customer Master'!$A$1:$A$50,'Customer Master'!$B$1:$B$50),"Not Found") -> Hazel Brooks | R27: {=_xlfn.IFS(P27="NA", "NA", P27<=2, "Fast", P27>2, "Slow")} -> Slow | S27: =_xlfn.XLOOKUP(C27, 'Product Master'!$A$1:$A$23, 'Product Master'!$B$1:$B$23, "Not Found") -> Backpack
A28: ORD0027 | B28: CUST018 | C28: PROD008 | D28: South | E28: 70 | F28: 2 | G28: 140 | H28: Amazon Pay | I28: In Transit | J28: Amazon Logistics | K28: 44942 | N28: =IF(OR(I28="Cancelled",M28<>""),"Yes","No") -> No | O28: =_xlfn.XLOOKUP(C28, 'Product Master'!$A$2:$A$23, 'Product Master'!$C$2:$C$23) -> Books | P28: =IF(L28<>"", L28-K28, "NA") -> NA | Q28: =IFERROR(_xlfn.XLOOKUP(B28,'Customer Master'!$A$1:$A$50,'Customer Master'!$B$1:$B$50),"Not Found") -> Grace Scott | R28: {=_xlfn.IFS(P28="NA", "NA", P28<=2, "Fast", P28>2, "Slow")} -> NA | S28: =_xlfn.XLOOKUP(C28, 'Product Master'!$A$1:$A$23, 'Product Master'!$B$1:$B$23, "Not Found") -> Textbook
A29: ORD0028 | B29: CUST018 | C29: PROD018 | D29: Central | E29: 97 | F29: 3 | G29: 291 | H29: Credit Card | I29: In Transit | J29: Amazon Logistics | K29: 45208 | N29: =IF(OR(I29="Cancelled",M29<>""),"Yes","No") -> No | O29: =_xlfn.XLOOKUP(C29, 'Product Master'!$A$2:$A$23, 'Product Master'!$C$2:$C$23) -> Toys | P29: =IF(L29<>"", L29-K29, "NA") -> NA | Q29: =IFERROR(_xlfn.XLOOKUP(B29,'Customer Master'!$A$1:$A$50,'Customer Master'!$B$1:$B$50),"Not Found") -> Grace Scott | R29: {=_xlfn.IFS(P29="NA", "NA", P29<=2, "Fast", P29>2, "Slow")} -> NA | S29: =_xlfn.XLOOKUP(C29, 'Product Master'!$A$1:$A$23, 'Product Master'!$B$1:$B$23, "Not Found") -> Doll House
A30: ORD0029 | B30: CUST007 | C30: PROD021 | D30: East | E30: 37 | F30: 3 | G30: 111 | H30: Apple Pay | I30: Cancelled | J30: DHL | K30: 45206 | M30: 45209 | N30: =IF(OR(I30="Cancelled",M30<>""),"Yes","No") -> Yes | O30: =_xlfn.XLOOKUP(C30, 'Product Master'!$A$2:$A$23, 'Product Master'!$C$2:$C$23) -> Home | P30: =IF(L30<>"", L30-K30, "NA") -> NA | Q30: =IFERROR(_xlfn.XLOOKUP(B30,'Customer Master'!$A$1:$A$50,'Customer Master'!$B$1:$B$50),"Not Found") -> Liam Walker | R30: {=_xlfn.IFS(P30="NA", "NA", P30<=2, "Fast", P30>2, "Slow")} -> NA | S30: =_xlfn.XLOOKUP(C30, 'Product Master'!$A$1:$A$23, 'Product Master'!$B$1:$B$23, "Not Found") -> Wall Clock
A31: ORD0030 | B31: CUST008 | C31: PROD008 | D31: North | E31: 69 | F31: 5 | G31: 345 | H31: Amazon Pay | I31: In Transit | J31: Amazon Logistics | K31: 44971 | N31: =IF(OR(I31="Cancelled",M31<>""),"Yes","No") -> No | O31: =_xlfn.XLOOKUP(C31, 'Product Master'!$A$2:$A$23, 'Product Master'!$C$2:$C$23) -> Books | P31: =IF(L31<>"", L31-K31, "NA") -> NA | Q31: =IFERROR(_xlfn.XLOOKUP(B31,'Customer Master'!$A$1:$A$50,'Customer Master'!$B$1:$B$50),"Not Found") -> Harper Young | R31: {=_xlfn.IFS(P31="NA", "NA", P31<=2, "Fast", P31>2, "Slow")} -> NA | S31: =_xlfn.XLOOKUP(C31, 'Product Master'!$A$1:$A$23, 'Product Master'!$B$1:$B$23, "Not Found") -> Textbook
A32: ORD0031 | B32: CUST014 | C32: PROD002 | D32: North | E32: 42 | F32: 5 | G32: 210 | H32: Amazon Pay | I32: In Transit | J32: UPS | K32: 45011 | N32: =IF(OR(I32="Cancelled",M32<>""),"Yes","No") -> No | O32: =_xlfn.XLOOKUP(C32, 'Product Master'!$A$2:$A$23, 'Product Master'!$C$2:$C$23) -> Toys | P32: =IF(L32<>"", L32-K32, "NA") -> NA | Q32: =IFERROR(_xlfn.XLOOKUP(B32,'Customer Master'!$A$1:$A$50,'Customer Master'!$B$1:$B$50),"Not Found") -> Harper Young | R32: {=_xlfn.IFS(P32="NA", "NA", P32<=2, "Fast", P32>2, "Slow")} -> NA | S32: =_xlfn.XLOOKUP(C32, 'Product Master'!$A$1:$A$23, 'Product Master'!$B$1:$B$23, "Not Found") -> Action Figure
A33: ORD0032 | B33: CUST037 | C33: PROD009 | D33: East | E33: 11 | F33: 5 | G33: 55 | H33: Debit Card | I33: Cancelled | J33: FedEx | K33: 45092 | M33: 45099 | N33: =IF(OR(I33="Cancelled",M33<>""),"Yes","No") -> Yes | O33: =_xlfn.XLOOKUP(C33, 'Product Master'!$A$2:$A$23, 'Product Master'!$C$2:$C$23) -> Books | P33: =IF(L33<>"", L33-K33, "NA") -> NA | Q33: =IFERROR(_xlfn.XLOOKUP(B33,'Customer Master'!$A$1:$A$50,'Customer Master'!$B$1:$B$50),"Not Found") -> Emily Johnson | R33: {=_xlfn.IFS(P33="NA", "NA", P33<=2, "Fast", P33>2, "Slow")} -> NA | S33: =_xlfn.XLOOKUP(C33, 'Product Master'!$A$1:$A$23, 'Product Master'!$B$1:$B$23, "Not Found") -> Magazine
A34: ORD0033 | B34: CUST016 | C34: PROD005 | D34: South | E34: 27 | F34: 2 | G34: 54 | H34: Apple Pay | I34: Delivered | J34: USPS | K34: 45068 | L34: 45069 | N34: =IF(OR(I34="Cancelled",M34<>""),"Yes","No") -> No | O34: =_xlfn.XLOOKUP(C34, 'Product Master'!$A$2:$A$23, 'Product Master'!$C$2:$C$23) -> Fashion | P34: =IF(L34<>"", L34-K34, "NA") -> 1 | Q34: =IFERROR(_xlfn.XLOOKUP(B34,'Customer Master'!$A$1:$A$50,'Customer Master'!$B$1:$B$50),"Not Found") -> Elijah Lewis | R34: {=_xlfn.IFS(P34="NA", "NA", P34<=2, "Fast", P34>2, "Slow")} -> Fast | S34: =_xlfn.XLOOKUP(C34, 'Product Master'!$A$1:$A$23, 'Product Master'!$B$1:$B$23, "Not Found") -> T-Shirt
A35: ORD0034 | B35: CUST025 | C35: PROD015 | D35: South | E35: 21 | F35: 1 | G35: 21 | H35: Amazon Pay | I35: In Transit | J35: DHL | K35: 45250 | N35: =IF(OR(I35="Cancelled",M35<>""),"Yes","No") -> No | O35: =_xlfn.XLOOKUP(C35, 'Product Master'!$A$2:$A$23, 'Product Master'!$C$2:$C$23) -> Books | P35: =IF(L35<>"", L35-K35, "NA") -> NA | Q35: =IFERROR(_xlfn.XLOOKUP(B35,'Customer Master'!$A$1:$A$50,'Customer Master'!$B$1:$B$50),"Not Found") -> Emma King | R35: {=_xlfn.IFS(P35="NA", "NA", P35<=2, "Fast", P35>2, "Slow")} -> NA | S35: =_xlfn.XLOOKUP(C35, 'Product Master'!$A$1:$A$23, 'Product Master'!$B$1:$B$23, "Not Found") -> Novel
A36: ORD0035 | B36: CUST032 | C36: PROD011 | D36: South | E36: 172 | F36: 1 | G36: 172 | H36: PayPal | I36: Delivered | J36: USPS | K36: 45282 | L36: 45286 | N36: =IF(OR(I36="Cancelled",M36<>""),"Yes","No") -> No | O36: =_xlfn.XLOOKUP(C36, 'Product Master'!$A$2:$A$23, 'Product Master'!$C$2:$C$23) -> Electronics | P36: =IF(L36<>"", L36-K36, "NA") -> 4 | Q36: =IFERROR(_xlfn.XLOOKUP(B36,'Customer Master'!$A$1:$A$50,'Customer Master'!$B$1:$B$50),"Not Found") -> Luke Gray | R36: {=_xlfn.IFS(P36="NA", "NA", P36<=2, "Fast", P36>2, "Slow")} -> Slow | S36: =_xlfn.XLOOKUP(C36, 'Product Master'!$A$1:$A$23, 'Product Master'!$B$1:$B$23, "Not Found") -> Headphones
A37: ORD0036 | B37: CUST014 | C37: PROD016 | D37: North | E37: 212 | F37: 3 | G37: 636 | H37: Amazon Pay | I37: In Transit | J37: UPS | K37: 45130 | N37: =IF(OR(I37="Cancelled",M37<>""),"Yes","No") -> No | O37: =_xlfn.XLOOKUP(C37, 'Product Master'!$A$2:$A$23, 'Product Master'!$C$2:$C$23) -> Home | P37: =IF(L37<>"", L37-K37, "NA") -> NA | Q37: =IFERROR(_xlfn.XLOOKUP(B37,'Customer Master'!$A$1:$A$50,'Customer Master'!$B$1:$B$50),"Not Found") -> Harper Young | R37: {=_xlfn.IFS(P37="NA", "NA", P37<=2, "Fast", P37>2, "Slow")} -> NA | S37: =_xlfn.XLOOKUP(C37, 'Product Master'!$A$1:$A$23, 'Product Master'!$B$1:$B$23, "Not Found") -> Cookware Set Pro
A38: ORD0037 | B38: CUST044 | C38: PROD002 | D38: East | E38: 41 | F38: 4 | G38: 164 | H38: Credit Card | I38: Delivered | J38: Amazon Logistics | K38: 45216 | L38: 45221 | N38: =IF(OR(I38="Cancelled",M38<>""),"Yes","No") -> No | O38: =_xlfn.XLOOKUP(C38, 'Product Master'!$A$2:$A$23, 'Product Master'!$C$2:$C$23) -> Toys | P38: =IF(L38<>"", L38-K38, "NA") -> 5 | Q38: =IFERROR(_xlfn.XLOOKUP(B38,'Customer Master'!$A$1:$A$50,'Customer Master'!$B$1:$B$50),"Not Found") -> Grace Ward | R38: {=_xlfn.IFS(P38="NA", "NA", P38<=2, "Fast", P38>2, "Slow")} -> Slow | S38: =_xlfn.XLOOKUP(C38, 'Product Master'!$A$1:$A$23, 'Product Master'!$B$1:$B$23, "Not Found") -> Action Figure
A39: ORD0038 | B39: CUST028 | C39: PROD007 | D39: North | E39: 32 | F39: 2 | G39: 64 | H39: Debit Card | I39: Cancelled | J39: FedEx | K39: 45160 | M39: 45162 | N39: =IF(OR(I39="Cancelled",M39<>""),"Yes","No") -> Yes | O39: =_xlfn.XLOOKUP(C39, 'Product Master'!$A$2:$A$23, 'Product Master'!$C$2:$C$23) -> Toys | P39: =IF(L39<>"", L39-K39, "NA") -> NA | Q39: =IFERROR(_xlfn.XLOOKUP(B39,'Customer Master'!$A$1:$A$50,'Customer Master'!$B$1:$B$50),"Not Found") -> Lily Bennett | R39: {=_xlfn.IFS(P39="NA", "NA", P39<=2, "Fast", P39>2, "Slow")} -> NA | S39: =_xlfn.XLOOKUP(C39, 'Product Master'!$A$1:$A$23, 'Product Master'!$B$1:$B$23, "Not Found") -> Puzzle
A40: ORD0039 | B40: CUST024 | C40: PROD022 | D40: East | E40: 66 | F40: 2 | G40: 132 | H40: Apple Pay | I40: In Transit | J40: DHL | K40: 45262 | N40: =IF(OR(I40="Cancelled",M40<>""),"Yes","No") -> No | O40: =_xlfn.XLOOKUP(C40, 'Product Master'!$A$2:$A$23, 'Product Master'!$C$2:$C$23) -> Fashion | P40: =IF(L40<>"", L40-K40, "NA") -> NA | Q40: =IFERROR(_xlfn.XLOOKUP(B40,'Customer Master'!$A$1:$A$50,'Customer Master'!$B$1:$B$50),"Not Found") -> Scarlett Murphy | R40: {=_xlfn.IFS(P40="NA", "NA", P40<=2, "Fast", P40>2, "Slow")} -> NA | S40: =_xlfn.XLOOKUP(C40, 'Product Master'!$A$1:$A$23, 'Product Master'!$B$1:$B$23, "Not Found") -> Backpack
A41: ORD0040 | B41: CUST006 | C41: PROD004 | D41: East | E41: 62 | F41: 4 | G41: 248 | H41: Debit Card | I41: In Transit | J41: UPS | K41: 45285 | N41: =IF(OR(I41="Cancelled",M41<>""),"Yes","No") -> No | O41: =_xlfn.XLOOKUP(C41, 'Product Master'!$A$2:$A$23, 'Product Master'!$C$2:$C$23) -> Toys | P41: =IF(L41<>"", L41-K41, "NA") -> NA | Q41: =IFERROR(_xlfn.XLOOKUP(B41,'Customer Master'!$A$1:$A$50,'Customer Master'!$B$1:$B$50),"Not Found") -> Ava Robinson | R41: {=_xlfn.IFS(P41="NA", "NA", P41<=2, "Fast", P41>2, "Slow")} -> NA | S41: =_xlfn.XLOOKUP(C41, 'Product Master'!$A$1:$A$23, 'Product Master'!$B$1:$B$23, "Not Found") -> Leg Set
A42: ORD0041 | B42: CUST001 | C42: PROD011 | D42: West | E42: 173 | F42: 4 | G42: 692 | H42: Apple Pay | I42: Delivered | J42: UPS | K42: 45192 | L42: 45199 | N42: =IF(OR(I42="Cancelled",M42<>""),"Yes","No") -> No | O42: =_xlfn.XLOOKUP(C42, 'Product Master'!$A$2:$A$23, 'Product Master'!$C$2:$C$23) -> Electronics | P42: =IF(L42<>"", L42-K42, "NA") -> 7 | Q42: =IFERROR(_xlfn.XLOOKUP(B42,'Customer Master'!$A$1:$A$50,'Customer Master'!$B$1:$B$50),"Not Found") -> James Miller | R42: {=_xlfn.IFS(P42="NA", "NA", P42<=2, "Fast", P42>2, "Slow")} -> Slow | S42: =_xlfn.XLOOKUP(C42, 'Product Master'!$A$1:$A$23, 'Product Master'!$B$1:$B$23, "Not Found") -> Headphones
A43: ORD0042 | B43: CUST007 | C43: PROD004 | D43: West | E43: 63 | F43: 3 | G43: 189 | H43: Apple Pay | I43: Delivered | J43: UPS | K43: 45123 | L43: 45125 | N43: =IF(OR(I43="Cancelled",M43<>""),"Yes","No") -> No | O43: =_xlfn.XLOOKUP(C43, 'Product Master'!$A$2:$A$23, 'Product Master'!$C$2:$C$23) -> Toys | P43: =IF(L43<>"", L43-K43, "NA") -> 2 | Q43: =IFERROR(_xlfn.XLOOKUP(B43,'Customer Master'!$A$1:$A$50,'Customer Master'!$B$1:$B$50),"Not Found") -> Liam Walker | R43: {=_xlfn.IFS(P43="NA", "NA", P43<=2, "Fast", P43>2, "Slow")} -> Fast | S43: =_xlfn.XLOOKUP(C43, 'Product Master'!$A$1:$A$23, 'Product Master'!$B$1:$B$23, "Not Found") -> Leg Set
A44: ORD0043 | B44: CUST040 | C44: PROD021 | D44: West | E44: 36 | F44: 3 | G44: 108 | H44: Debit Card | I44: Cancelled | J44: USPS | K44: 44962 | M44: 44968 | N44: =IF(OR(I44="Cancelled",M44<>""),"Yes","No") -> Yes | O44: =_xlfn.XLOOKUP(C44, 'Product Master'!$A$2:$A$23, 'Product Master'!$C$2:$C$23) -> Home | P44: =IF(L44<>"", L44-K44, "NA") -> NA | Q44: =IFERROR(_xlfn.XLOOKUP(B44,'Customer Master'!$A$1:$A$50,'Customer Master'!$B$1:$B$50),"Not Found") -> Benjamin Clark | R44: {=_xlfn.IFS(P44="NA", "NA", P44<=2, "Fast", P44>2, "Slow")} -> NA | S44: =_xlfn.XLOOKUP(C44, 'Product Master'!$A$1:$A$23, 'Product Master'!$B$1:$B$23, "Not Found") -> Wall Clock
A45: ORD0044 | B45: CUST006 | C45: PROD004 | D45: Central | E45: 62 | F45: 1 | G45: 62 | H45: Apple Pay | I45: Cancelled | J45: Amazon Logistics | K45: 45278 | M45: 45283 | N45: =IF(OR(I45="Cancelled",M45<>""),"Yes","No") -> Yes | O45: =_xlfn.XLOOKUP(C45, 'Product Master'!$A$2:$A$23, 'Product Master'!$C$2:$C$23) -> Toys | P45: =IF(L45<>"", L45-K45, "NA") -> NA | Q45: =IFERROR(_xlfn.XLOOKUP(B45,'Customer Master'!$A$1:$A$50,'Customer Master'!$B$1:$B$50),"Not Found") -> Ava Robinson | R45: {=_xlfn.IFS(P45="NA", "NA", P45<=2, "Fast", P45>2, "Slow")} -> NA | S45: =_xlfn.XLOOKUP(C45, 'Product Master'!$A$1:$A$23, 'Product Master'!$B$1:$B$23, "Not Found") -> Leg Set
A46: ORD0045 | B46: CUST042 | C46: PROD003 | D46: Central | E46: 137 | F46: 5 | G46: 685 | H46: Amazon Pay | I46: Cancelled | J46: FedEx | K46: 45088 | M46: 45091 | N46: =IF(OR(I46="Cancelled",M46<>""),"Yes","No") -> Yes | O46: =_xlfn.XLOOKUP(C46, 'Product Master'!$A$2:$A$23, 'Product Master'!$C$2:$C$23) -> Home | P46: =IF(L46<>"", L46-K46, "NA") -> NA | Q46: =IFERROR(_xlfn.XLOOKUP(B46,'Customer Master'!$A$1:$A$50,'Customer Master'!$B$1:$B$50),"Not Found") -> Noah Wilson | R46: {=_xlfn.IFS(P46="NA", "NA", P46<=2, "Fast", P46>2, "Slow")} -> NA | S46: =_xlfn.XLOOKUP(C46, 'Product Master'!$A$1:$A$23, 'Product Master'!$B$1:$B$23, "Not Found") -> Cookware Set
A47: ORD0046 | B47: CUST039 | C47: PROD017 | D47: North | E47: 73 | F47: 4 | G47: 292 | H47: Credit Card | I47: Delivered | J47: Amazon Logistics | K47: 45264 | L47: 45268 | N47: =IF(OR(I47="Cancelled",M47<>""),"Yes","No") -> No | O47: =_xlfn.XLOOKUP(C47, 'Product Master'!$A$2:$A$23, 'Product Master'!$C$2:$C$23) -> Electronics | P47: =IF(L47<>"", L47-K47, "NA") -> 4 | Q47: =IFERROR(_xlfn.XLOOKUP(B47,'Customer Master'!$A$1:$A$50,'Customer Master'!$B$1:$B$50),"Not Found") -> Logan Ramirez | R47: {=_xlfn.IFS(P47="NA", "NA", P47<=2, "Fast", P47>2, "Slow")} -> Slow | S47: =_xlfn.XLOOKUP(C47, 'Product Master'!$A$1:$A$23, 'Product Master'!$B$1:$B$23, "Not Found") -> Gaming Mouse
A48: ORD0047 | B48: CUST041 | C48: PROD020 | D48: North | E48: 104 | F48: 1 | G48: 104 | H48: PayPal | I48: Delivered | J48: Amazon Logistics | K48: 45124 | L48: 45126 | N48: =IF(OR(I48="Cancelled",M48<>""),"Yes","No") -> No | O48: =_xlfn.XLOOKUP(C48, 'Product Master'!$A$2:$A$23, 'Product Master'!$C$2:$C$23) -> Electronics | P48: =IF(L48<>"", L48-K48, "NA") -> 2 | Q48: =IFERROR(_xlfn.XLOOKUP(B48,'Customer Master'!$A$1:$A$50,'Customer Master'!$B$1:$B$50),"Not Found") -> Jacob Price | R48: {=_xlfn.IFS(P48="NA", "NA", P48<=2, "Fast", P48>2, "Slow")} -> Fast | S48: =_xlfn.XLOOKUP(C48, 'Product Master'!$A$1:$A$23, 'Product Master'!$B$1:$B$23, "Not Found") -> Bluetooth Speaker
A49: ORD0048 | B49: CUST044 | C49: PROD006 | D49: East | E49: 97 | F49: 1 | G49: 97 | H49: Amazon Pay | I49: Delivered | J49: FedEx | K49: 45218 | L49: 45223 | N49: =IF(OR(I49="Cancelled",M49<>""),"Yes","No") -> No | O49: =_xlfn.XLOOKUP(C49, 'Product Master'!$A$2:$A$23, 'Product Master'!$C$2:$C$23) -> Fashion | P49: =IF(L49<>"", L49-K49, "NA") -> 5 | Q49: =IFERROR(_xlfn.XLOOKUP(B49,'Customer Master'!$A$1:$A$50,'Customer Master'!$B$1:$B$50),"Not Found") -> Grace Ward | R49: {=_xlfn.IFS(P49="NA", "NA", P49<=2, "Fast", P49>2, "Slow")} -> Slow | S49: =_xlfn.XLOOKUP(C49, 'Product Master'!$A$1:$A$23, 'Product Master'!$B$1:$B$23, "Not Found") -> Shoes
A50: ORD0049 | B50: CUST026 | C50: PROD017 | D50: South | E50: 73 | F50: 5 | G50: 365 | H50: Apple Pay | I50: In Transit | J50: Amazon Logistics | K50: 45061 | N50: =IF(OR(I50="Cancelled",M50<>""),"Yes","No") -> No | O50: =_xlfn.XLOOKUP(C50, 'Product Master'!$A$2:$A$23, 'Product Master'!$C$2:$C$23) -> Electronics | P50: =IF(L50<>"", L50-K50, "NA") -> NA | Q50: =IFERROR(_xlfn.XLOOKUP(B50,'Customer Master'!$A$1:$A$50,'Customer Master'!$B$1:$B$50),"Not Found") -> Zoe Mitchell | R50: {=_xlfn.IFS(P50="NA", "NA", P50<=2, "Fast", P50>2, "Slow")} -> NA | S50: =_xlfn.XLOOKUP(C50, 'Product Master'!$A$1:$A$23, 'Product Master'!$B$1:$B$23, "Not Found") -> Gaming Mouse
A51: ORD0050 | B51: CUST040 | C51: PROD005 | D51: East | E51: 27 | F51: 3 | G51: 81 | H51: Amazon Pay | I51: Delivered | J51: UPS | K51: 44969 | L51: 44976 | N51: =IF(OR(I51="Cancelled",M51<>""),"Yes","No") -> No | O51: =_xlfn.XLOOKUP(C51, 'Product Master'!$A$2:$A$23, 'Product Master'!$C$2:$C$23) -> Fashion | P51: =IF(L51<>"", L51-K51, "NA") -> 7 | Q51: =IFERROR(_xlfn.XLOOKUP(B51,'Customer Master'!$A$1:$A$50,'Customer Master'!$B$1:$B$50),"Not Found") -> Benjamin Clark | R51: {=_xlfn.IFS(P51="NA", "NA", P51<=2, "Fast", P51>2, "Slow")} -> Slow | S51: =_xlfn.XLOOKUP(C51, 'Product Master'!$A$1:$A$23, 'Product Master'!$B$1:$B$23, "Not Found") -> T-Shirt
A52: ORD0051 | B52: CUST041 | C52: PROD021 | D52: North | E52: 37 | F52: 1 | G52: 37 | H52: Apple Pay | I52: In Transit | J52: UPS | K52: 45201 | N52: =IF(OR(I52="Cancelled",M52<>""),"Yes","No") -> No | O52: =_xlfn.XLOOKUP(C52, 'Product Master'!$A$2:$A$23, 'Product Master'!$C$2:$C$23) -> Home | P52: =IF(L52<>"", L52-K52, "NA") -> NA | Q52: =IFERROR(_xlfn.XLOOKUP(B52,'Customer Master'!$A$1:$A$50,'Customer Master'!$B$1:$B$50),"Not Found") -> Jacob Price | R52: {=_xlfn.IFS(P52="NA", "NA", P52<=2, "Fast", P52>2, "Slow")} -> NA | S52: =_xlfn.XLOOKUP(C52, 'Product Master'!$A$1:$A$23, 'Product Master'!$B$1:$B$23, "Not Found") -> Wall Clock
A53: ORD0052 | B53: CUST008 | C53: PROD015 | D53: North | E53: 22 | F53: 1 | G53: 22 | H53: Debit Card | I53: Delivered | J53: FedEx | K53: 44956 | L53: 44958 | N53: =IF(OR(I53="Cancelled",M53<>""),"Yes","No") -> No | O53: =_xlfn.XLOOKUP(C53, 'Product Master'!$A$2:$A$23, 'Product Master'!$C$2:$C$23) -> Books | P53: =IF(L53<>"", L53-K53, "NA") -> 2 | Q53: =IFERROR(_xlfn.XLOOKUP(B53,'Customer Master'!$A$1:$A$50,'Customer Master'!$B$1:$B$50),"Not Found") -> Harper Young | R53: {=_xlfn.IFS(P53="NA", "NA", P53<=2, "Fast", P53>2, "Slow")} -> Fast | S53: =_xlfn.XLOOKUP(C53, 'Product Master'!$A$1:$A$23, 'Product Master'!$B$1:$B$23, "Not Found") -> Novel
A54: ORD0053 | B54: CUST011 | C54: PROD016 | D54: Central | E54: 218 | F54: 5 | G54: 1090 | H54: PayPal | I54: Delivered | J54: DHL | K54: 45289 | L54: 45292 | N54: =IF(OR(I54="Cancelled",M54<>""),"Yes","No") -> No | O54: =_xlfn.XLOOKUP(C54, 'Product Master'!$A$2:$A$23, 'Product Master'!$C$2:$C$23) -> Home | P54: =IF(L54<>"", L54-K54, "NA") -> 3 | Q54: =IFERROR(_xlfn.XLOOKUP(B54,'Customer Master'!$A$1:$A$50,'Customer Master'!$B$1:$B$50),"Not Found") -> Mason Hall | R54: {=_xlfn.IFS(P54="NA", "NA", P54<=2, "Fast", P54>2, "Slow")} -> Slow | S54: =_xlfn.XLOOKUP(C54, 'Product Master'!$A$1:$A$23, 'Product Master'!$B$1:$B$23, "Not Found") -> Cookware Set Pro
A55: ORD0054 | B55: CUST018 | C55: PROD004 | D55: North | E55: 64 | F55: 1 | G55: 64 | H55: Apple Pay | I55: Cancelled | J55: USPS | K55: 44991 | M55: 44998 | N55: =IF(OR(I55="Cancelled",M55<>""),"Yes","No") -> Yes | O55: =_xlfn.XLOOKUP(C55, 'Product Master'!$A$2:$A$23, 'Product Master'!$C$2:$C$23) -> Toys | P55: =IF(L55<>"", L55-K55, "NA") -> NA | Q55: =IFERROR(_xlfn.XLOOKUP(B55,'Customer Master'!$A$1:$A$50,'Customer Master'!$B$1:$B$50),"Not Found") -> Grace Scott | R55: {=_xlfn.IFS(P55="NA", "NA", P55<=2, "Fast", P55>2, "Slow")} -> NA | S55: =_xlfn.XLOOKUP(C55, 'Product Master'!$A$1:$A$23, 'Product Master'!$B$1:$B$23, "Not Found") -> Leg Set
A56: ORD0055 | B56: CUST037 | C56: PROD021 | D56: Central | E56: 36 | F56: 4 | G56: 144 | H56: PayPal | I56: Delivered | J56: Amazon Logistics | K56: 44959 | L56: 44963 | N56: =IF(OR(I56="Cancelled",M56<>""),"Yes","No") -> No | O56: =_xlfn.XLOOKUP(C56, 'Product Master'!$A$2:$A$23, 'Product Master'!$C$2:$C$23) -> Home | P56: =IF(L56<>"", L56-K56, "NA") -> 4 | Q56: =IFERROR(_xlfn.XLOOKUP(B56,'Customer Master'!$A$1:$A$50,'Customer Master'!$B$1:$B$50),"Not Found") -> Emily Johnson | R56: {=_xlfn.IFS(P56="NA", "NA", P56<=2, "Fast", P56>2, "Slow")} -> Slow | S56: =_xlfn.XLOOKUP(C56, 'Product Master'!$A$1:$A$23, 'Product Master'!$B$1:$B$23, "Not Found") -> Wall Clock
A57: ORD0056 | B57: CUST017 | C57: PROD004 | D57: West | E57: 65 | F57: 1 | G57: 65 | H57: Amazon Pay | I57: Delivered | J57: FedEx | K57: 45217 | L57: 45220 | N57: =IF(OR(I57="Cancelled",M57<>""),"Yes","No") -> No | O57: =_xlfn.XLOOKUP(C57, 'Product Master'!$A$2:$A$23, 'Product Master'!$C$2:$C$23) -> Toys | P57: =IF(L57<>"", L57-K57, "NA") -> 3 | Q57: =IFERROR(_xlfn.XLOOKUP(B57,'Customer Master'!$A$1:$A$50,'Customer Master'!$B$1:$B$50),"Not Found") -> Emma King | R57: {=_xlfn.IFS(P57="NA", "NA", P57<=2, "Fast", P57>2, "Slow")} -> Slow | S57: =_xlfn.XLOOKUP(C57, 'Product Master'!$A$1:$A$23, 'Product Master'!$B$1:$B$23, "Not Found") -> Leg Set
A58: ORD0057 | B58: CUST025 | C58: PROD005 | D58: Central | E58: 26 | F58: 1 | G58: 26 | H58: Apple Pay | I58: Delivered | J58: DHL | K58: 44933 | L58: 44935 | N58: =IF(OR(I58="Cancelled",M58<>""),"Yes","No") -> No | O58: =_xlfn.XLOOKUP(C58, 'Product Master'!$A$2:$A$23, 'Product Master'!$C$2:$C$23) -> Fashion | P58: =IF(L58<>"", L58-K58, "NA") -> 2 | Q58: =IFERROR(_xlfn.XLOOKUP(B58,'Customer Master'!$A$1:$A$50,'Customer Master'!$B$1:$B$50),"Not Found") -> Emma King | R58: {=_xlfn.IFS(P58="NA", "NA", P58<=2, "Fast", P58>2, "Slow")} -> Fast | S58: =_xlfn.XLOOKUP(C58, 'Product Master'!$A$1:$A$23, 'Product Master'!$B$1:$B$23, "Not Found") -> T-Shirt
A59: ORD0058 | B59: CUST021 | C59: PROD009 | D59: North | E59: 11 | F59: 5 | G59: 55 | H59: Credit Card | I59: In Transit | J59: FedEx | K59: 45054 | N59: =IF(OR(I59="Cancelled",M59<>""),"Yes","No") -> No | O59: =_xlfn.XLOOKUP(C59, 'Product Master'!$A$2:$A$23, 'Product Master'!$C$2:$C$23) -> Books | P59: =IF(L59<>"", L59-K59, "NA") -> NA | Q59: =IFERROR(_xlfn.XLOOKUP(B59,'Customer Master'!$A$1:$A$50,'Customer Master'!$B$1:$B$50),"Not Found") -> Zoe Mitchell | R59: {=_xlfn.IFS(P59="NA", "NA", P59<=2, "Fast", P59>2, "Slow")} -> NA | S59: =_xlfn.XLOOKUP(C59, 'Product Master'!$A$1:$A$23, 'Product Master'!$B$1:$B$23, "Not Found") -> Magazine
A60: ORD0059 | B60: CUST003 | C60: PROD013 | D60: North | E60: 195 | F60: 4 | G60: 780 | H60: PayPal | I60: Cancelled | J60: FedEx | K60: 45018 | M60: 45021 | N60: =IF(OR(I60="Cancelled",M60<>""),"Yes","No") -> Yes | O60: =_xlfn.XLOOKUP(C60, 'Product Master'!$A$2:$A$23, 'Product Master'!$C$2:$C$23) -> Home | P60: =IF(L60<>"", L60-K60, "NA") -> NA | Q60: =IFERROR(_xlfn.XLOOKUP(B60,'Customer Master'!$A$1:$A$50,'Customer Master'!$B$1:$B$50),"Not Found") -> Ethan Davis | R60: {=_xlfn.IFS(P60="NA", "NA", P60<=2, "Fast", P60>2, "Slow")} -> NA | S60: =_xlfn.XLOOKUP(C60, 'Product Master'!$A$1:$A$23, 'Product Master'!$B$1:$B$23, "Not Found") -> Vacuum Cleaner
A61: ORD0060 | B61: CUST019 | C61: PROD019 | D61: West | E61: 44 | F61: 5 | G61: 220 | H61: Apple Pay | I61: Cancelled | J61: USPS | K61: 45210 | M61: 45211 | N61: =IF(OR(I61="Cancelled",M61<>""),"Yes","No") -> Yes | O61: =_xlfn.XLOOKUP(C61, 'Product Master'!$A$2:$A$23, 'Product Master'!$C$2:$C$23) -> Fashion | P61: =IF(L61<>"", L61-K61, "NA") -> NA | Q61: =IFERROR(_xlfn.XLOOKUP(B61,'Customer Master'!$A$1:$A$50,'Customer Master'!$B$1:$B$50),"Not Found") -> Ava Robinson | R61: {=_xlfn.IFS(P61="NA", "NA", P61<=2, "Fast", P61>2, "Slow")} -> NA | S61: =_xlfn.XLOOKUP(C61, 'Product Master'!$A$1:$A$23, 'Product Master'!$B$1:$B$23, "Not Found") -> Formal Shirt
A62: ORD0061 | B62: CUST035 | C62: PROD008 | D62: East | E62: 69 | F62: 4 | G62: 276 | H62: Debit Card | I62: In Transit | J62: DHL | K62: 45179 | N62: =IF(OR(I62="Cancelled",M62<>""),"Yes","No") -> No | O62: =_xlfn.XLOOKUP(C62, 'Product Master'!$A$2:$A$23, 'Product Master'!$C$2:$C$23) -> Books | P62: =IF(L62<>"", L62-K62, "NA") -> NA | Q62: =IFERROR(_xlfn.XLOOKUP(B62,'Customer Master'!$A$1:$A$50,'Customer Master'!$B$1:$B$50),"Not Found") -> Scarlett Adams | R62: {=_xlfn.IFS(P62="NA", "NA", P62<=2, "Fast", P62>2, "Slow")} -> NA | S62: =_xlfn.XLOOKUP(C62, 'Product Master'!$A$1:$A$23, 'Product Master'!$B$1:$B$23, "Not Found") -> Textbook
A63: ORD0062 | B63: CUST022 | C63: PROD001 | D63: North | E63: 815 | F63: 4 | G63: 3260 | H63: Credit Card | I63: Delivered | J63: USPS | K63: 45252 | L63: 45259 | N63: =IF(OR(I63="Cancelled",M63<>""),"Yes","No") -> No | O63: =_xlfn.XLOOKUP(C63, 'Product Master'!$A$2:$A$23, 'Product Master'!$C$2:$C$23) -> Electronics | P63: =IF(L63<>"", L63-K63, "NA") -> 7 | Q63: =IFERROR(_xlfn.XLOOKUP(B63,'Customer Master'!$A$1:$A$50,'Customer Master'!$B$1:$B$50),"Not Found") -> Elijah Lewis | R63: {=_xlfn.IFS(P63="NA", "NA", P63<=2, "Fast", P63>2, "Slow")} -> Slow | S63: =_xlfn.XLOOKUP(C63, 'Product Master'!$A$1:$A$23, 'Product Master'!$B$1:$B$23, "Not Found") -> Smartphone
A64: ORD0063 | B64: CUST004 | C64: PROD005 | D64: East | E64: 27 | F64: 1 | G64: 27 | H64: Debit Card | I64: In Transit | J64: Amazon Logistics | K64: 45048 | N64: =IF(OR(I64="Cancelled",M64<>""),"Yes","No") -> No | O64: =_xlfn.XLOOKUP(C64, 'Product Master'!$A$2:$A$23, 'Product Master'!$C$2:$C$23) -> Fashion | P64: =IF(L64<>"", L64-K64, "NA") -> NA | Q64: =IFERROR(_xlfn.XLOOKUP(B64,'Customer Master'!$A$1:$A$50,'Customer Master'!$B$1:$B$50),"Not Found") -> Noah Wilson | R64: {=_xlfn.IFS(P64="NA", "NA", P64<=2, "Fast", P64>2, "Slow")} -> NA | S64: =_xlfn.XLOOKUP(C64, 'Product Master'!$A$1:$A$23, 'Product Master'!$B$1:$B$23, "Not Found") -> T-Shirt
A65: ORD0064 | B65: CUST048 | C65: PROD003 | D65: West | E65: 139 | F65: 5 | G65: 695 | H65: Apple Pay | I65: Delivered | J65: USPS | K65: 45285 | L65: 45289 | N65: =IF(OR(I65="Cancelled",M65<>""),"Yes","No") -> No | O65: =_xlfn.XLOOKUP(C65, 'Product Master'!$A$2:$A$23, 'Product Master'!$C$2:$C$23) -> Home | P65: =IF(L65<>"", L65-K65, "NA") -> 4 | Q65: =IFERROR(_xlfn.XLOOKUP(B65,'Customer Master'!$A$1:$A$50,'Customer Master'!$B$1:$B$50),"Not Found") -> Noah Wilson | R65: {=_xlfn.IFS(P65="NA", "NA", P65<=2, "Fast", P65>2, "Slow")} -> Slow | S65: =_xlfn.XLOOKUP(C65, 'Product Master'!$A$1:$A$23, 'Product Master'!$B$1:$B$23, "Not Found") -> Cookware Set
A66: ORD0065 | B66: CUST009 | C66: PROD008 | D66: South | E66: 69 | F66: 3 | G66: 207 | H66: PayPal | I66: Cancelled | J66: Amazon Logistics | K66: 45217 | M66: 45219 | N66: =IF(OR(I66="Cancelled",M66<>""),"Yes","No") -> Yes | O66: =_xlfn.XLOOKUP(C66, 'Product Master'!$A$2:$A$23, 'Product Master'!$C$2:$C$23) -> Books | P66: =IF(L66<>"", L66-K66, "NA") -> NA | Q66: =IFERROR(_xlfn.XLOOKUP(B66,'Customer Master'!$A$1:$A$50,'Customer Master'!$B$1:$B$50),"Not Found") -> Jackson Allen | R66: {=_xlfn.IFS(P66="NA", "NA", P66<=2, "Fast", P66>2, "Slow")} -> NA | S66: =_xlfn.XLOOKUP(C66, 'Product Master'!$A$1:$A$23, 'Product Master'!$B$1:$B$23, "Not Found") -> Textbook
A67: ORD0066 | B67: CUST009 | C67: PROD019 | D67: West | E67: 42 | F67: 1 | G67: 42 | H67: Apple Pay | I67: Cancelled | J67: DHL | K67: 45066 | M67: 45067 | N67: =IF(OR(I67="Cancelled",M67<>""),"Yes","No") -> Yes | O67: =_xlfn.XLOOKUP(C67, 'Product Master'!$A$2:$A$23, 'Product Master'!$C$2:$C$23) -> Fashion | P67: =IF(L67<>"", L67-K67, "NA") -> NA | Q67: =IFERROR(_xlfn.XLOOKUP(B67,'Customer Master'!$A$1:$A$50,'Customer Master'!$B$1:$B$50),"Not Found") -> Jackson Allen | R67: {=_xlfn.IFS(P67="NA", "NA", P67<=2, "Fast", P67>2, "Slow")} -> NA | S67: =_xlfn.XLOOKUP(C67, 'Product Master'!$A$1:$A$23, 'Product Master'!$B$1:$B$23, "Not Found") -> Formal Shirt
A68: ORD0067 | B68: CUST050 | C68: PROD007 | D68: North | E68: 31 | F68: 4 | G68: 124 | H68: Credit Card | I68: Delivered | J68: UPS | K68: 45135 | L68: 45137 | N68: =IF(OR(I68="Cancelled",M68<>""),"Yes","No") -> No | O68: =_xlfn.XLOOKUP(C68, 'Product Master'!$A$2:$A$23, 'Product Master'!$C$2:$C$23) -> Toys | P68: =IF(L68<>"", L68-K68, "NA") -> 2 | Q68: =IFERROR(_xlfn.XLOOKUP(B68,'Customer Master'!$A$1:$A$50,'Customer Master'!$B$1:$B$50),"Not Found") -> Not Found | R68: {=_xlfn.IFS(P68="NA", "NA", P68<=2, "Fast", P68>2, "Slow")} -> Fast | S68: =_xlfn.XLOOKUP(C68, 'Product Master'!$A$1:$A$23, 'Product Master'!$B$1:$B$23, "Not Found") -> Puzzle
A69: ORD0068 | B69: CUST045 | C69: PROD020 | D69: West | E69: 104 | F69: 3 | G69: 312 | H69: Credit Card | I69: In Transit | J69: UPS | K69: 45278 | N69: =IF(OR(I69="Cancelled",M69<>""),"Yes","No") -> No | O69: =_xlfn.XLOOKUP(C69, 'Product Master'!$A$2:$A$23, 'Product Master'!$C$2:$C$23) -> Electronics | P69: =IF(L69<>"", L69-K69, "NA") -> NA | Q69: =IFERROR(_xlfn.XLOOKUP(B69,'Customer Master'!$A$1:$A$50,'Customer Master'!$B$1:$B$50),"Not Found") -> Emily Johnson | R69: {=_xlfn.IFS(P69="NA", "NA", P69<=2, "Fast", P69>2, "Slow")} -> NA | S69: =_xlfn.XLOOKUP(C69, 'Product Master'!$A$1:$A$23, 'Product Master'!$B$1:$B$23, "Not Found") -> Bluetooth Speaker
A70: ORD0069 | B70: CUST044 | C70: PROD010 | D70: East | E70: 58 | F70: 2 | G70: 116 | H70: Apple Pay | I70: Cancelled | J70: USPS | K70: 45109 | M70: 45114 | N70: =IF(OR(I70="Cancelled",M70<>""),"Yes","No") -> Yes | O70: =_xlfn.XLOOKUP(C70, 'Product Master'!$A$2:$A$23, 'Product Master'!$C$2:$C$23) -> Fashion | P70: =IF(L70<>"", L70-K70, "NA") -> NA | Q70: =IFERROR(_xlfn.XLOOKUP(B70,'Customer Master'!$A$1:$A$50,'Customer Master'!$B$1:$B$50),"Not Found") -> Grace Ward | R70: {=_xlfn.IFS(P70="NA", "NA", P70<=2, "Fast", P70>2, "Slow")} -> NA | S70: =_xlfn.XLOOKUP(C70, 'Product Master'!$A$1:$A$23, 'Product Master'!$B$1:$B$23, "Not Found") -> Jeans
A71: ORD0070 | B71: CUST009 | C71: PROD004 | D71: West | E71: 62 | F71: 2 | G71: 124 | H71: Debit Card | I71: Cancelled | J71: DHL | K71: 45208 | M71: 45209 | N71: =IF(OR(I71="Cancelled",M71<>""),"Yes","No") -> Yes | O71: =_xlfn.XLOOKUP(C71, 'Product Master'!$A$2:$A$23, 'Product Master'!$C$2:$C$23) -> Toys | P71: =IF(L71<>"", L71-K71, "NA") -> NA | Q71: =IFERROR(_xlfn.XLOOKUP(B71,'Customer Master'!$A$1:$A$50,'Customer Master'!$B$1:$B$50),"Not Found") -> Jackson Allen | R71: {=_xlfn.IFS(P71="NA", "NA", P71<=2, "Fast", P71>2, "Slow")} -> NA | S71: =_xlfn.XLOOKUP(C71, 'Product Master'!$A$1:$A$23, 'Product Master'!$B$1:$B$23, "Not Found") -> Leg Set
A72: ORD0071 | B72: CUST006 | C72: PROD019 | D72: East | E72: 43 | F72: 1 | G72: 43 | H72: Credit Card | I72: Delivered | J72: Amazon Logistics | K72: 45278 | L72: 45285 | N72: =IF(OR(I72="Cancelled",M72<>""),"Yes","No") -> No | O72: =_xlfn.XLOOKUP(C72, 'Product Master'!$A$2:$A$23, 'Product Master'!$C$2:$C$23) -> Fashion | P72: =IF(L72<>"", L72-K72, "NA") -> 7 | Q72: =IFERROR(_xlfn.XLOOKUP(B72,'Customer Master'!$A$1:$A$50,'Customer Master'!$B$1:$B$50),"Not Found") -> Ava Robinson | R72: {=_xlfn.IFS(P72="NA", "NA", P72<=2, "Fast", P72>2, "Slow")} -> Slow | S72: =_xlfn.XLOOKUP(C72, 'Product Master'!$A$1:$A$23, 'Product Master'!$B$1:$B$23, "Not Found") -> Formal Shirt
A73: ORD0072 | B73: CUST022 | C73: PROD004 | D73: East | E73: 62 | F73: 4 | G73: 248 | H73: Debit Card | I73: In Transit | J73: Amazon Logistics | K73: 44992 | N73: =IF(OR(I73="Cancelled",M73<>""),"Yes","No") -> No | O73: =_xlfn.XLOOKUP(C73, 'Product Master'!$A$2:$A$23, 'Product Master'!$C$2:$C$23) -> Toys | P73: =IF(L73<>"", L73-K73, "NA") -> NA | Q73: =IFERROR(_xlfn.XLOOKUP(B73,'Customer Master'!$A$1:$A$50,'Customer Master'!$B$1:$B$50),"Not Found") -> Elijah Lewis | R73: {=_xlfn.IFS(P73="NA", "NA", P73<=2, "Fast", P73>2, "Slow")} -> NA | S73: =_xlfn.XLOOKUP(C73, 'Product Master'!$A$1:$A$23, 'Product Master'!$B$1:$B$23, "Not Found") -> Leg Set
A74: ORD0073 | B74: CUST028 | C74: PROD006 | D74: North | E74: 95 | F74: 2 | G74: 190 | H74: PayPal | I74: Cancelled | J74: UPS | K74: 45129 | M74: 45132 | N74: =IF(OR(I74="Cancelled",M74<>""),"Yes","No") -> Yes | O74: =_xlfn.XLOOKUP(C74, 'Product Master'!$A$2:$A$23, 'Product Master'!$C$2:$C$23) -> Fashion | P74: =IF(L74<>"", L74-K74, "NA") -> NA | Q74: =IFERROR(_xlfn.XLOOKUP(B74,'Customer Master'!$A$1:$A$50,'Customer Master'!$B$1:$B$50),"Not Found") -> Lily Bennett | R74: {=_xlfn.IFS(P74="NA", "NA", P74<=2, "Fast", P74>2, "Slow")} -> NA | S74: =_xlfn.XLOOKUP(C74, 'Product Master'!$A$1:$A$23, 'Product Master'!$B$1:$B$23, "Not Found") -> Shoes
A75: ORD0074 | B75: CUST016 | C75: PROD021 | D75: Central | E75: 36 | F75: 4 | G75: 144 | H75: Apple Pay | I75: Delivered | J75: FedEx | K75: 44944 | L75: 44950 | N75: =IF(OR(I75="Cancelled",M75<>""),"Yes","No") -> No | O75: =_xlfn.XLOOKUP(C75, 'Product Master'!$A$2:$A$23, 'Product Master'!$C$2:$C$23) -> Home | P75: =IF(L75<>"", L75-K75, "NA") -> 6 | Q75: =IFERROR(_xlfn.XLOOKUP(B75,'Customer Master'!$A$1:$A$50,'Customer Master'!$B$1:$B$50),"Not Found") -> Elijah Lewis | R75: {=_xlfn.IFS(P75="NA", "NA", P75<=2, "Fast", P75>2, "Slow")} -> Slow | S75: =_xlfn.XLOOKUP(C75, 'Product Master'!$A$1:$A$23, 'Product Master'!$B$1:$B$23, "Not Found") -> Wall Clock
A76: ORD0075 | B76: CUST042 | C76: PROD017 | D76: East | E76: 73 | F76: 5 | G76: 365 | H76: Apple Pay | I76: In Transit | J76: DHL | K76: 45070 | N76: =IF(OR(I76="Cancelled",M76<>""),"Yes","No") -> No | O76: =_xlfn.XLOOKUP(C76, 'Product Master'!$A$2:$A$23, 'Product Master'!$C$2:$C$23) -> Electronics | P76: =IF(L76<>"", L76-K76, "NA") -> NA | Q76: =IFERROR(_xlfn.XLOOKUP(B76,'Customer Master'!$A$1:$A$50,'Customer Master'!$B$1:$B$50),"Not Found") -> Noah Wilson | R76: {=_xlfn.IFS(P76="NA", "NA", P76<=2, "Fast", P76>2, "Slow")} -> NA | S76: =_xlfn.XLOOKUP(C76, 'Product Master'!$A$1:$A$23, 'Product Master'!$B$1:$B$23, "Not Found") -> Gaming Mouse
A77: ORD0076 | B77: CUST023 | C77: PROD019 | D77: North | E77: 43 | F77: 4 | G77: 172 | H77: Debit Card | I77: Delivered | J77: DHL | K77: 45172 | L77: 45178 | N77: =IF(OR(I77="Cancelled",M77<>""),"Yes","No") -> No | O77: =_xlfn.XLOOKUP(C77, 'Product Master'!$A$2:$A$23, 'Product Master'!$C$2:$C$23) -> Fashion | P77: =IF(L77<>"", L77-K77, "NA") -> 6 | Q77: =IFERROR(_xlfn.XLOOKUP(B77,'Customer Master'!$A$1:$A$50,'Customer Master'!$B$1:$B$50),"Not Found") -> Charlotte Reed | R77: {=_xlfn.IFS(P77="NA", "NA", P77<=2, "Fast", P77>2, "Slow")} -> Slow | S77: =_xlfn.XLOOKUP(C77, 'Product Master'!$A$1:$A$23, 'Product Master'!$B$1:$B$23, "Not Found") -> Formal Shirt
A78: ORD0077 | B78: CUST004 | C78: PROD016 | D78: West | E78: 214 | F78: 5 | G78: 1070 | H78: Debit Card | I78: Delivered | J78: UPS | K78: 45232 | L78: 45234 | N78: =IF(OR(I78="Cancelled",M78<>""),"Yes","No") -> No | O78: =_xlfn.XLOOKUP(C78, 'Product Master'!$A$2:$A$23, 'Product Master'!$C$2:$C$23) -> Home | P78: =IF(L78<>"", L78-K78, "NA") -> 2 | Q78: =IFERROR(_xlfn.XLOOKUP(B78,'Customer Master'!$A$1:$A$50,'Customer Master'!$B$1:$B$50),"Not Found") -> Noah Wilson | R78: {=_xlfn.IFS(P78="NA", "NA", P78<=2, "Fast", P78>2, "Slow")} -> Fast | S78: =_xlfn.XLOOKUP(C78, 'Product Master'!$A$1:$A$23, 'Product Master'!$B$1:$B$23, "Not Found") -> Cookware Set Pro
A79: ORD0078 | B79: CUST048 | C79: PROD002 | D79: Central | E79: 42 | F79: 2 | G79: 84 | H79: Apple Pay | I79: Cancelled | J79: UPS | K79: 45263 | M79: 45266 | N79: =IF(OR(I79="Cancelled",M79<>""),"Yes","No") -> Yes | O79: =_xlfn.XLOOKUP(C79, 'Product Master'!$A$2:$A$23, 'Product Master'!$C$2:$C$23) -> Toys | P79: =IF(L79<>"", L79-K79, "NA") -> NA | Q79: =IFERROR(_xlfn.XLOOKUP(B79,'Customer Master'!$A$1:$A$50,'Customer Master'!$B$1:$B$50),"Not Found") -> Noah Wilson | R79: {=_xlfn.IFS(P79="NA", "NA", P79<=2, "Fast", P79>2, "Slow")} -> NA | S79: =_xlfn.XLOOKUP(C79, 'Product Master'!$A$1:$A$23, 'Product Master'!$B$1:$B$23, "Not Found") -> Action Figure
A80: ORD0079 | B80: CUST048 | C80: PROD012 | D80: North | E80: 46 | F80: 1 | G80: 46 | H80: Amazon Pay | I80: In Transit | J80: UPS | K80: 45017 | N80: =IF(OR(I80="Cancelled",M80<>""),"Yes","No") -> No | O80: =_xlfn.XLOOKUP(C80, 'Product Master'!$A$2:$A$23, 'Product Master'!$C$2:$C$23) -> Home | P80: =IF(L80<>"", L80-K80, "NA") -> NA | Q80: =IFERROR(_xlfn.XLOOKUP(B80,'Customer Master'!$A$1:$A$50,'Customer Master'!$B$1:$B$50),"Not Found") -> Noah Wilson | R80: {=_xlfn.IFS(P80="NA", "NA", P80<=2, "Fast", P80>2, "Slow")} -> NA | S80: =_xlfn.XLOOKUP(C80, 'Product Master'!$A$1:$A$23, 'Product Master'!$B$1:$B$23, "Not Found") -> Lamp
A81: ORD0080 | B81: CUST032 | C81: PROD018 | D81: East | E81: 95 | F81: 4 | G81: 380 | H81: Credit Card | I81: Delivered | J81: UPS | K81: 45215 | L81: 45218 | N81: =IF(OR(I81="Cancelled",M81<>""),"Yes","No") -> No | O81: =_xlfn.XLOOKUP(C81, 'Product Master'!$A$2:$A$23, 'Product Master'!$C$2:$C$23) -> Toys | P81: =IF(L81<>"", L81-K81, "NA") -> 3 | Q81: =IFERROR(_xlfn.XLOOKUP(B81,'Customer Master'!$A$1:$A$50,'Customer Master'!$B$1:$B$50),"Not Found") -> Luke Gray | R81: {=_xlfn.IFS(P81="NA", "NA", P81<=2, "Fast", P81>2, "Slow")} -> Slow | S81: =_xlfn.XLOOKUP(C81, 'Product Master'!$A$1:$A$23, 'Product Master'!$B$1:$B$23, "Not Found") -> Doll House
A82: ORD0081 | B82: CUST001 | C82: PROD011 | D82: West | E82: 174 | F82: 2 | G82: 348 | H82: PayPal | I82: In Transit | J82: UPS | K82: 45235 | N82: =IF(OR(I82="Cancelled",M82<>""),"Yes","No") -> No | O82: =_xlfn.XLOOKUP(C82, 'Product Master'!$A$2:$A$23, 'Product Master'!$C$2:$C$23) -> Electronics | P82: =IF(L82<>"", L82-K82, "NA") -> NA | Q82: =IFERROR(_xlfn.XLOOKUP(B82,'Customer Master'!$A$1:$A$50,'Customer Master'!$B$1:$B$50),"Not Found") -> James Miller | R82: {=_xlfn.IFS(P82="NA", "NA", P82<=2, "Fast", P82>2, "Slow")} -> NA | S82: =_xlfn.XLOOKUP(C82, 'Product Master'!$A$1:$A$23, 'Product Master'!$B$1:$B$23, "Not Found") -> Headphones
A83: ORD0082 | B83: CUST046 | C83: PROD005 | D83: North | E83: 27 | F83: 5 | G83: 135 | H83: Credit Card | I83: Cancelled | J83: Amazon Logistics | K83: 45092 | M83: 45095 | N83: =IF(OR(I83="Cancelled",M83<>""),"Yes","No") -> Yes | O83: =_xlfn.XLOOKUP(C83, 'Product Master'!$A$2:$A$23, 'Product Master'!$C$2:$C$23) -> Fashion | P83: =IF(L83<>"", L83-K83, "NA") -> NA | Q83: =IFERROR(_xlfn.XLOOKUP(B83,'Customer Master'!$A$1:$A$50,'Customer Master'!$B$1:$B$50),"Not Found") -> Emily Johnson | R83: {=_xlfn.IFS(P83="NA", "NA", P83<=2, "Fast", P83>2, "Slow")} -> NA | S83: =_xlfn.XLOOKUP(C83, 'Product Master'!$A$1:$A$23, 'Product Master'!$B$1:$B$23, "Not Found") -> T-Shirt
A84: ORD0083 | B84: CUST021 | C84: PROD005 | D84: South | E84: 27 | F84: 4 | G84: 108 | H84: PayPal | I84: Delivered | J84: USPS | K84: 45227 | L84: 45229 | N84: =IF(OR(I84="Cancelled",M84<>""),"Yes","No") -> No | O84: =_xlfn.XLOOKUP(C84, 'Product Master'!$A$2:$A$23, 'Product Master'!$C$2:$C$23) -> Fashion | P84: =IF(L84<>"", L84-K84, "NA") -> 2 | Q84: =IFERROR(_xlfn.XLOOKUP(B84,'Customer Master'!$A$1:$A$50,'Customer Master'!$B$1:$B$50),"Not Found") -> Zoe Mitchell | R84: {=_xlfn.IFS(P84="NA", "NA", P84<=2, "Fast", P84>2, "Slow")} -> Fast | S84: =_xlfn.XLOOKUP(C84, 'Product Master'!$A$1:$A$23, 'Product Master'!$B$1:$B$23, "Not Found") -> T-Shirt
A85: ORD0084 | B85: CUST015 | C85: PROD022 | D85: South | E85: 65 | F85: 2 | G85: 130 | H85: PayPal | I85: In Transit | J85: DHL | K85: 45282 | N85: =IF(OR(I85="Cancelled",M85<>""),"Yes","No") -> No | O85: =_xlfn.XLOOKUP(C85, 'Product Master'!$A$2:$A$23, 'Product Master'!$C$2:$C$23) -> Fashion | P85: =IF(L85<>"", L85-K85, "NA") -> NA | Q85: =IFERROR(_xlfn.XLOOKUP(B85,'Customer Master'!$A$1:$A$50,'Customer Master'!$B$1:$B$50),"Not Found") -> Ava White | R85: {=_xlfn.IFS(P85="NA", "NA", P85<=2, "Fast", P85>2, "Slow")} -> NA | S85: =_xlfn.XLOOKUP(C85, 'Product Master'!$A$1:$A$23, 'Product Master'!$B$1:$B$23, "Not Found") -> Backpack
A86: ORD0085 | B86: CUST045 | C86: PROD019 | D86: East | E86: 43 | F86: 5 | G86: 215 | H86: Debit Card | I86: In Transit | J86: DHL | K86: 44992 | N86: =IF(OR(I86="Cancelled",M86<>""),"Yes","No") -> No | O86: =_xlfn.XLOOKUP(C86, 'Product Master'!$A$2:$A$23, 'Product Master'!$C$2:$C$23) -> Fashion | P86: =IF(L86<>"", L86-K86, "NA") -> NA | Q86: =IFERROR(_xlfn.XLOOKUP(B86,'Customer Master'!$A$1:$A$50,'Customer Master'!$B$1:$B$50),"Not Found") -> Emily Johnson | R86: {=_xlfn.IFS(P86="NA", "NA", P86<=2, "Fast", P86>2, "Slow")} -> NA | S86: =_xlfn.XLOOKUP(C86, 'Product Master'!$A$1:$A$23, 'Product Master'!$B$1:$B$23, "Not Found") -> Formal Shirt
A87: ORD0086 | B87: CUST007 | C87: PROD016 | D87: West | E87: 210 | F87: 1 | G87: 210 | H87: PayPal | I87: In Transit | J87: UPS | K87: 45240 | N87: =IF(OR(I87="Cancelled",M87<>""),"Yes","No") -> No | O87: =_xlfn.XLOOKUP(C87, 'Product Master'!$A$2:$A$23, 'Product Master'!$C$2:$C$23) -> Home | P87: =IF(L87<>"", L87-K87, "NA") -> NA | Q87: =IFERROR(_xlfn.XLOOKUP(B87,'Customer Master'!$A$1:$A$50,'Customer Master'!$B$1:$B$50),"Not Found") -> Liam Walker | R87: {=_xlfn.IFS(P87="NA", "NA", P87<=2, "Fast", P87>2, "Slow")} -> NA | S87: =_xlfn.XLOOKUP(C87, 'Product Master'!$A$1:$A$23, 'Product Master'!$B$1:$B$23, "Not Found") -> Cookware Set Pro
A88: ORD0087 | B88: CUST043 | C88: PROD021 | D88: South | E88: 37 | F88: 3 | G88: 111 | H88: Credit Card | I88: In Transit | J88: UPS | K88: 45252 | N88: =IF(OR(I88="Cancelled",M88<>""),"Yes","No") -> No | O88: =_xlfn.XLOOKUP(C88, 'Product Master'!$A$2:$A$23, 'Product Master'!$C$2:$C$23) -> Home | P88: =IF(L88<>"", L88-K88, "NA") -> NA | Q88: =IFERROR(_xlfn.XLOOKUP(B88,'Customer Master'!$A$1:$A$50,'Customer Master'!$B$1:$B$50),"Not Found") -> Lily Reed | R88: {=_xlfn.IFS(P88="NA", "NA", P88<=2, "Fast", P88>2, "Slow")} -> NA | S88: =_xlfn.XLOOKUP(C88, 'Product Master'!$A$1:$A$23, 'Product Master'!$B$1:$B$23, "Not Found") -> Wall Clock
A89: ORD0088 | B89: CUST007 | C89: PROD001 | D89: South | E89: 788 | F89: 4 | G89: 3152 | H89: Debit Card | I89: In Transit | J89: Amazon Logistics | K89: 45054 | N89: =IF(OR(I89="Cancelled",M89<>""),"Yes","No") -> No | O89: =_xlfn.XLOOKUP(C89, 'Product Master'!$A$2:$A$23, 'Product Master'!$C$2:$C$23) -> Electronics | P89: =IF(L89<>"", L89-K89, "NA") -> NA | Q89: =IFERROR(_xlfn.XLOOKUP(B89,'Customer Master'!$A$1:$A$50,'Customer Master'!$B$1:$B$50),"Not Found") -> Liam Walker | R89: {=_xlfn.IFS(P89="NA", "NA", P89<=2, "Fast", P89>2, "Slow")} -> NA | S89: =_xlfn.XLOOKUP(C89, 'Product Master'!$A$1:$A$23, 'Product Master'!$B$1:$B$23, "Not Found") -> Smartphone
A90: ORD0089 | B90: CUST007 | C90: PROD016 | D90: West | E90: 217 | F90: 5 | G90: 1085 | H90: Debit Card | I90: In Transit | J90: FedEx | K90: 45120 | N90: =IF(OR(I90="Cancelled",M90<>""),"Yes","No") -> No | O90: =_xlfn.XLOOKUP(C90, 'Product Master'!$A$2:$A$23, 'Product Master'!$C$2:$C$23) -> Home | P90: =IF(L90<>"", L90-K90, "NA") -> NA | Q90: =IFERROR(_xlfn.XLOOKUP(B90,'Customer Master'!$A$1:$A$50,'Customer Master'!$B$1:$B$50),"Not Found") -> Liam Walker | R90: {=_xlfn.IFS(P90="NA", "NA", P90<=2, "Fast", P90>2, "Slow")} -> NA | S90: =_xlfn.XLOOKUP(C90, 'Product Master'!$A$1:$A$23, 'Product Master'!$B$1:$B$23, "Not Found") -> Cookware Set Pro
A91: ORD0090 | B91: CUST007 | C91: PROD003 | D91: West | E91: 138 | F91: 4 | G91: 552 | H91: Credit Card | I91: In Transit | J91: FedEx | K91: 44944 | N91: =IF(OR(I91="Cancelled",M91<>""),"Yes","No") -> No | O91: =_xlfn.XLOOKUP(C91, 'Product Master'!$A$2:$A$23, 'Product Master'!$C$2:$C$23) -> Home | P91: =IF(L91<>"", L91-K91, "NA") -> NA | Q91: =IFERROR(_xlfn.XLOOKUP(B91,'Customer Master'!$A$1:$A$50,'Customer Master'!$B$1:$B$50),"Not Found") -> Liam Walker | R91: {=_xlfn.IFS(P91="NA", "NA", P91<=2, "Fast", P91>2, "Slow")} -> NA | S91: =_xlfn.XLOOKUP(C91, 'Product Master'!$A$1:$A$23, 'Product Master'!$B$1:$B$23, "Not Found") -> Cookware Set
A92: ORD0091 | B92: CUST031 | C92: PROD001 | D92: Central | E92: 803 | F92: 2 | G92: 1606 | H92: Apple Pay | I92: Delivered | J92: FedEx | K92: 45100 | L92: 45106 | N92: =IF(OR(I92="Cancelled",M92<>""),"Yes","No") -> No | O92: =_xlfn.XLOOKUP(C92, 'Product Master'!$A$2:$A$23, 'Product Master'!$C$2:$C$23) -> Electronics | P92: =IF(L92<>"", L92-K92, "NA") -> 6 | Q92: =IFERROR(_xlfn.XLOOKUP(B92,'Customer Master'!$A$1:$A$50,'Customer Master'!$B$1:$B$50),"Not Found") -> Mason Collins | R92: {=_xlfn.IFS(P92="NA", "NA", P92<=2, "Fast", P92>2, "Slow")} -> Slow | S92: =_xlfn.XLOOKUP(C92, 'Product Master'!$A$1:$A$23, 'Product Master'!$B$1:$B$23, "Not Found") -> Smartphone
A93: ORD0092 | B93: CUST013 | C93: PROD014 | D93: North | E93: 248 | F93: 5 | G93: 1240 | H93: PayPal | I93: Cancelled | J93: UPS | K93: 44978 | M93: 44982 | N93: =IF(OR(I93="Cancelled",M93<>""),"Yes","No") -> Yes | O93: =_xlfn.XLOOKUP(C93, 'Product Master'!$A$2:$A$23, 'Product Master'!$C$2:$C$23) -> Electronics | P93: =IF(L93<>"", L93-K93, "NA") -> NA | Q93: =IFERROR(_xlfn.XLOOKUP(B93,'Customer Master'!$A$1:$A$50,'Customer Master'!$B$1:$B$50),"Not Found") -> Olivia Martinez | R93: {=_xlfn.IFS(P93="NA", "NA", P93<=2, "Fast", P93>2, "Slow")} -> NA | S93: =_xlfn.XLOOKUP(C93, 'Product Master'!$A$1:$A$23, 'Product Master'!$B$1:$B$23, "Not Found") -> Smartwatch
A94: ORD0093 | B94: CUST036 | C94: PROD016 | D94: East | E94: 210 | F94: 3 | G94: 630 | H94: Apple Pay | I94: Delivered | J94: DHL | K94: 44976 | L94: 44978 | N94: =IF(OR(I94="Cancelled",M94<>""),"Yes","No") -> No | O94: =_xlfn.XLOOKUP(C94, 'Product Master'!$A$2:$A$23, 'Product Master'!$C$2:$C$23) -> Home | P94: =IF(L94<>"", L94-K94, "NA") -> 2 | Q94: =IFERROR(_xlfn.XLOOKUP(B94,'Customer Master'!$A$1:$A$50,'Customer Master'!$B$1:$B$50),"Not Found") -> Ethan Davis | R94: {=_xlfn.IFS(P94="NA", "NA", P94<=2, "Fast", P94>2, "Slow")} -> Fast | S94: =_xlfn.XLOOKUP(C94, 'Product Master'!$A$1:$A$23, 'Product Master'!$B$1:$B$23, "Not Found") -> Cookware Set Pro
A95: ORD0094 | B95: CUST013 | C95: PROD004 | D95: North | E95: 62 | F95: 2 | G95: 124 | H95: Credit Card | I95: Cancelled | J95: FedEx | K95: 45265 | M95: 45272 | N95: =IF(OR(I95="Cancelled",M95<>""),"Yes","No") -> Yes | O95: =_xlfn.XLOOKUP(C95, 'Product Master'!$A$2:$A$23, 'Product Master'!$C$2:$C$23) -> Toys | P95: =IF(L95<>"", L95-K95, "NA") -> NA | Q95: =IFERROR(_xlfn.XLOOKUP(B95,'Customer Master'!$A$1:$A$50,'Customer Master'!$B$1:$B$50),"Not Found") -> Olivia Martinez | R95: {=_xlfn.IFS(P95="NA", "NA", P95<=2, "Fast", P95>2, "Slow")} -> NA | S95: =_xlfn.XLOOKUP(C95, 'Product Master'!$A$1:$A$23, 'Product Master'!$B$1:$B$23, "Not Found") -> Leg Set
A96: ORD0095 | B96: CUST043 | C96: PROD009 | D96: South | E96: 11 | F96: 5 | G96: 55 | H96: Debit Card | I96: Cancelled | J96: Amazon Logistics | K96: 45084 | M96: 45089 | N96: =IF(OR(I96="Cancelled",M96<>""),"Yes","No") -> Yes | O96: =_xlfn.XLOOKUP(C96, 'Product Master'!$A$2:$A$23, 'Product Master'!$C$2:$C$23) -> Books | P96: =IF(L96<>"", L96-K96, "NA") -> NA | Q96: =IFERROR(_xlfn.XLOOKUP(B96,'Customer Master'!$A$1:$A$50,'Customer Master'!$B$1:$B$50),"Not Found") -> Lily Reed | R96: {=_xlfn.IFS(P96="NA", "NA", P96<=2, "Fast", P96>2, "Slow")} -> NA | S96: =_xlfn.XLOOKUP(C96, 'Product Master'!$A$1:$A$23, 'Product Master'!$B$1:$B$23, "Not Found") -> Magazine
A97: ORD0096 | B97: CUST017 | C97: PROD015 | D97: North | E97: 21 | F97: 2 | G97: 42 | H97: Amazon Pay | I97: Delivered | J97: UPS | K97: 45116 | L97: 45119 | N97: =IF(OR(I97="Cancelled",M97<>""),"Yes","No") -> No | O97: =_xlfn.XLOOKUP(C97, 'Product Master'!$A$2:$A$23, 'Product Master'!$C$2:$C$23) -> Books | P97: =IF(L97<>"", L97-K97, "NA") -> 3 | Q97: =IFERROR(_xlfn.XLOOKUP(B97,'Customer Master'!$A$1:$A$50,'Customer Master'!$B$1:$B$50),"Not Found") -> Emma King | R97: {=_xlfn.IFS(P97="NA", "NA", P97<=2, "Fast", P97>2, "Slow")} -> Slow | S97: =_xlfn.XLOOKUP(C97, 'Product Master'!$A$1:$A$23, 'Product Master'!$B$1:$B$23, "Not Found") -> Novel
A98: ORD0097 | B98: CUST023 | C98: PROD018 | D98: West | E98: 95 | F98: 5 | G98: 475 | H98: Amazon Pay | I98: Delivered | J98: Amazon Logistics | K98: 45283 | L98: 45286 | N98: =IF(OR(I98="Cancelled",M98<>""),"Yes","No") -> No | O98: =_xlfn.XLOOKUP(C98, 'Product Master'!$A$2:$A$23, 'Product Master'!$C$2:$C$23) -> Toys | P98: =IF(L98<>"", L98-K98, "NA") -> 3 | Q98: =IFERROR(_xlfn.XLOOKUP(B98,'Customer Master'!$A$1:$A$50,'Customer Master'!$B$1:$B$50),"Not Found") -> Charlotte Reed | R98: {=_xlfn.IFS(P98="NA", "NA", P98<=2, "Fast", P98>2, "Slow")} -> Slow | S98: =_xlfn.XLOOKUP(C98, 'Product Master'!$A$1:$A$23, 'Product Master'!$B$1:$B$23, "Not Found") -> Doll House
A99: ORD0098 | B99: CUST044 | C99: PROD016 | D99: South | E99: 215 | F99: 2 | G99: 430 | H99: PayPal | I99: Delivered | J99: Amazon Logistics | K99: 45194 | L99: 45199 | N99: =IF(OR(I99="Cancelled",M99<>""),"Yes","No") -> No | O99: =_xlfn.XLOOKUP(C99, 'Product Master'!$A$2:$A$23, 'Product Master'!$C$2:$C$23) -> Home | P99: =IF(L99<>"", L99-K99, "NA") -> 5 | Q99: =IFERROR(_xlfn.XLOOKUP(B99,'Customer Master'!$A$1:$A$50,'Customer Master'!$B$1:$B$50),"Not Found") -> Grace Ward | R99: {=_xlfn.IFS(P99="NA", "NA", P99<=2, "Fast", P99>2, "Slow")} -> Slow | S99: =_xlfn.XLOOKUP(C99, 'Product Master'!$A$1:$A$23, 'Product Master'!$B$1:$B$23, "Not Found") -> Cookware Set Pro
A100: ORD0099 | B100: CUST034 | C100: PROD019 | D100: West | E100: 43 | F100: 5 | G100: 215 | H100: Credit Card | I100: Cancelled | J100: UPS | K100: 44944 | M100: 44950 | N100: =IF(OR(I100="Cancelled",M100<>""),"Yes","No") -> Yes | O100: =_xlfn.XLOOKUP(C100, 'Product Master'!$A$2:$A$23, 'Product Master'!$C$2:$C$23) -> Fashion | P100: =IF(L100<>"", L100-K100, "NA") -> NA | Q100: =IFERROR(_xlfn.XLOOKUP(B100,'Customer Master'!$A$1:$A$50,'Customer Master'!$B$1:$B$50),"Not Found") -> Lily Simmons | R100: {=_xlfn.IFS(P100="NA", "NA", P100<=2, "Fast", P100>2, "Slow")} -> NA | S100: =_xlfn.XLOOKUP(C100, 'Product Master'!$A$1:$A$23, 'Product Master'!$B$1:$B$23, "Not Found") -> Formal Shirt
...

Sheet Product Master
A1: Product ID | B1: Product Name | C1: Category | D1: Cost Price | E1: Description
A2: PROD001 | B2: Smartphone | C2: Electronics | D2: 749 | E2: Latest model with 5G, dual SIM, and OLED display
A3: PROD002 | B3: Action Figure | C3: Toys | D3: 39 | E3: Collectible superhero action figure for ages 8+
A4: PROD003 | B4: Cookware Set | C4: Home | D4: 129 | E4: Non-stick 5-piece cookware set for daily use
A5: PROD004 | B5: Leg Set | C5: Toys | D5: 59 | E5: 300-piece creative building block toy set
A6: PROD005 | B6: T-Shirt | C6: Fashion | D6: 25 | E6: Cotton t-shirt, available in multiple colors
A7: PROD006 | B7: Shoes | C7: Fashion | D7: 89 | E7: Casual wear shoes for men and women
A8: PROD007 | B8: Puzzle | C8: Toys | D8: 29 | E8: 1000-piece jigsaw puzzle
A9: PROD008 | B9: Textbook | C9: Books | D9: 65 | E9: University-level textbook on computer science
A10: PROD009 | B10: Magazine | C10: Books | D10: 10 | E10: Monthly lifestyle magazine
A11: PROD010 | B11: Jeans | C11: Fashion | D11: 55 | E11: Slim fit denim jeans with stretch
A12: PROD011 | B12: Headphones | C12: Electronics | D12: 159 | E12: Wireless noise-cancelling over-ear headphones
A13: PROD012 | B13: Lamp | C13: Home | D13: 42 | E13: LED desk lamp with dimmable light
... A23: PROD022 | B23: Backpack | C23: Fashion | D23: 60 | E23: Waterproof backpack with laptop compartment

Sheet Region Master
A1: Region | B1: Sales Target
A2: Central | B2: 97500
A3: East | B3: 50500
A4: North | B4: 105000
A5: South | B5: 91500
A6: West | B6: 90750

Sheet Customer Master
A1: Customer ID | B1: Customer Name | C1: Customer Type | D1: City | E1: State
A2: CUST001 | B2: James Miller | C2: Business | D2: New York | E2: New York
A3: CUST002 | B3: Emily Johnson | C3: Prime | D3: Seattle | E3: Washington
A4: CUST003 | B4: Ethan Davis | C4: Prime | D4: Austin | E4: Texas
A5: CUST004 | B5: Noah Wilson | C5: Prime | D5: San Francisco | E5: California
A6: CUST005 | B6: Olivia Martinez | C6: Prime | D6: Seattle | E6: Washington
A7: CUST006 | B7: Ava Robinson | C7: Prime | D7: Chicago | E7: Illinois
A8: CUST007 | B8: Liam Walker | C8: Prime | D8: San Francisco | E8: California
A9: CUST008 | B9: Harper Young | C9: Business | D9: Dallas | E9: Texas
A10: CUST009 | B10: Jackson Allen | C10: Business | D10: Seattle | E10: Washington
A11: CUST010 | B11: Charlotte Harris | C11: Prime | D11: Chicago | E11: Illinois
A12: CUST011 | B12: Mason Hall | C12: Business | D12: Miami | E12: Florida
... A50: CUST049 | B50: Hazel Gray | C50: Business | D50: Chicago | E50: Illinois

Sheet Dashboard
AH4: Sum of Total Amount | AL4: Row Labels | AM4: Count of Order ID | AP4: Column Labels
AH5: 35258 | AL5: Leg Set | AM5: 8 | AP5: Fast | AQ5: NA | AR5: Slow | AS5: Grand Total | AT5: % of Fast Delivery
AL6: T-Shirt | AM6: 8 | AO6: Count of Order ID | AP6: 11 | AQ6: 66 | AR6: 23 | AS6: 100 | AT6: =AP6/(AP6+AR6) -> 0.32352941
AL7: Grand Total | AM7: 16

Sheet Q & A
A2: Brainstorming Reflection | I2: Answers
A3: ● What is the most successful product category in terms of revenue? | I3: Electronics
A4: ● Which region has the highest order cancellation rate? | I4: North
A5: ● How many orders were delivered within 2 days? | I5: 11
A6: ● How has the use of XLOOKUP simplified cross-sheet analysis? | I6: XLOOKUP simplified cross-sheet analysis by easily fetching required data from other sheets using common values. It is more efficient as compared to older VLOOKUP or HLOOKUP.
A7: ● What recommendations would you give to improve delivery performance? | I7: 1. Improve logistics in high delay regions
I8: 2. Optimize warehouse processing time
I9: 3. Use of real time order tracking

Sheet 2.1
A3: Sum of Total Amount | B3: Column Labels
A4: Row Labels | B4: Books | C4: Electronics | D4: Fashion | E4: Home | F4: Toys | G4: Grand Total
A5: Central | B5: 84 | C5: 2662 | D5: 210 | E5: 2063 | F5: 437 | G5: 5456
A6: East | B6: 394 | C6: 365 | D6: 711 | E6: 741 | F6: 1424 | G6: 3635
A7: North | B7: 464 | C7: 6522 | D7: 788 | E7: 2131 | F7: 586 | G7: 10491
A8: South | B8: 423 | C8: 3938 | D8: 1032 | E8: 1881 | F8: 43 | G8: 7317
A9: West | B9: 350 | C9: 1722 | D9: 1131 | E9: 4135 | F9: 1021 | G9: 8359
A10: Grand Total | B10: 1715 | C10: 15209 | D10: 3872 | E10: 10951 | F10: 3511 | G10: 35258

Sheet 2.2
A3: Row Labels | B3: Count of Order ID
A4: Cancelled | B4: 30
A5: Delivered | B5: 34
A6: In Transit | B6: 36
A7: Grand Total | B7: 100

Sheet 2.3
A1: Payment Method | B1: (All)
A2: Product Category | B2: (All)
A4: Row Labels
A5: Central
A6: East
A7: North
A8: South
A9: West
A10: Grand Total

Sheet 4.1
A3: Count of Order ID | B3: Column Labels
A4: Row Labels | B4: No | C4: Yes | D4: Grand Total | E4: Cancellation Rate
A5: Central | B5: 9 | C5: 5 | D5: 14 | E5: =C5/D5 -> 0.35714286
A6: East | B6: 15 | C6: 3 | D6: 18 | E6: =C6/D6 -> 0.16666667
A7: North | B7: 15 | C7: 10 | D7: 25 | E7: =C7/D7 -> 0.4
A8: South | B8: 16 | C8: 4 | D8: 20 | E8: =C8/D8 -> 0.2
A9: West | B9: 15 | C9: 8 | D9: 23 | E9: =C9/D9 -> 0.34782609
A10: Grand Total | B10: 70 | C10: 30 | D10: 100 | E10: =C10/D10 -> 0.3

Sheet 4.2
A3: Row Labels | B3: Sum of Total Amount
A4: Delivered | B4: 13656
A5: Grand Total | B5: 13656

Sheet 4.3.1
A3: Row Labels | B3: Sum of Total Amount
A4: Cancelled | B4: 6961
A5: Delivered | B5: 13656
A6: In Transit | B6: 14641
A7: Grand Total | B7: 35258

Sheet 4.3.2
B3: Column Labels | F3: Fast Delivery %
B4: Fast | C4: NA | D4: Slow | E4: Grand Total | F4: =B5/(B5+D5) -> 0.32352941
A5: Count of Order ID | B5: 11 | C5: 66 | D5: 23 | E5: 100

Sheet 4.3.3
A3: Row Labels | B3: Sum of Total Amount
A4: Central | B4: 5456
A5: East | B5: 3635
A6: North | B6: 10491
A7: South | B7: 7317
A8: West | B8: 8359
A9: Grand Total | B9: 35258

Sheet 4.3.4
A3: Row Labels | B3: Count of Order ID
A4: Leg Set | B4: 8
A5: T-Shirt | B5: 8
A6: Grand Total | B6: 16

Sheet RegionwiseSales1
A3: Row Labels | B3: Sum of High | C3: Sum of Low
A4: Central | B4: #N/A | C4: 5456
A5: East | B5: #N/A | C5: 3635
A6: North | B6: 10491 | C6: #N/A
A7: South | B7: 7317 | C7: #N/A
A8: West | B8: 8359 | C8: #N/A
A9: Grand Total | B9: 35258 | C9: #N/A

Sheet RegionwiseSales2
A2: Region | B2: Sales | C2: High | D2: Low
A3: Central | B3: 5456 | C3: =IF(B3>7000, B3, NA()) -> #N/A | D3: =IF(B3<=7000, B3, NA()) -> 5456
A4: East | B4: 3635 | C4: =IF(B4>7000, B4, NA()) -> #N/A | D4: =IF(B4<=7000, B4, NA()) -> 3635
A5: North | B5: 10491 | C5: =IF(B5>7000, B5, NA()) -> 10491 | D5: =IF(B5<=7000, B5, NA()) -> #N/A
A6: South | B6: 7317 | C6: =IF(B6>7000, B6, NA()) -> 7317 | D6: =IF(B6<=7000, B6, NA()) -> #N/A
A7: West | B7: 8359 | C7: =IF(B7>7000, B7, NA()) -> 8359 | D7: =IF(B7<=7000, B7, NA()) -> #N/A

Sheet PaymentMethod
A3: Row Labels | B3: Sum of Total Amount
A4: Amazon Pay | B4: 4719
A5: Apple Pay | B5: 6144
A6: Credit Card | B6: 9398
A7: Debit Card | B7: 8348
A8: PayPal | B8: 6649
A9: Grand Total | B9: 35258

Sheet DeliveryStatus
A3: Row Labels | B3: Count of Order ID
A4: Cancelled | B4: 30
A5: Delivered | B5: 34
A6: In Transit | B6: 36
A7: Grand Total | B7: 100

Sheet MonthlySales
A3: Row Labels | B3: Sum of Total Amount
A4: Jan | B4: 1099
A5: Feb | B5: 3712
A6: Mar | B6: 905
A7: Apr | B7: 2637
A8: May | B8: 4940
A9: Jun | B9: 2599
A10: Jul | B10: 3315
A11: Aug | B11: 782
A12: Sep | B12: 1570
A13: Oct | B13: 2920
A14: Nov | B14: 6312
A15: Dec | B15: 4467
A16: Grand Total | B16: 35258

Sheet AvgOrderValue
B3: Count of Order ID | C3: Sum of Total Amount | D3: Avg Order Value
B4: 100 | C4: 35258 | D4: =C4/B4 -> 352.58
